<mbm>
  <entry id="0">
    <source>ダミーメッセージ{f801}</source>
    <target>ダミーメッセージ{f801}</target>
  </entry>
  <entry id="1">
    <source>{f871}{0100}{f816}我{f817}わ{f818}が{f816}主{f817}あるじ{f818}は ただひとり{f801}その{f816}名{f817}な{f818}を{f816}馳{f817}は{f818}せし アキュラのみ{f801}{f802}この{f816}唯一{f817}ゆいいつ{f818}{f816}至高{f817}しこう{f818}の {f816}古{f817}ふる{f818}き{f816}盟約{f817}めいやく{f818}{f801}{f816}何人{f817}なんぴと{f818}も{f816}破{f817}やぶ{f818}れはせぬぞ{f801}{f802}</source>
    <target>{f871}{0100}{f816}我{f817}わ{f818}が{f816}主{f817}あるじ{f818}は ただひとり{f801}その{f816}名{f817}な{f818}を{f816}馳{f817}は{f818}せし アキュラのみ{f801}{f802}この{f816}唯一{f817}ゆいいつ{f818}{f816}至高{f817}しこう{f818}の {f816}古{f817}ふる{f818}き{f816}盟約{f817}めいやく{f818}{f801}{f816}何人{f817}なんぴと{f818}も{f816}破{f817}やぶ{f818}れはせぬぞ{f801}{f802}</target>
  </entry>
  <entry id="2">
    <source>NOT USED{f801}</source>
    <target>NOT USED{f801}</target>
  </entry>
  <entry id="3">
    <source>{f871}{0100}NOT USED{f801}{f802}</source>
    <target>{f871}{0100}NOT USED{f801}{f802}</target>
  </entry>
  <entry id="4">
    <source>NOT USED{f801}</source>
    <target>NOT USED{f801}</target>
  </entry>
  <entry id="5">
    <source>{f871}{0100}…サムライどもよ{f801}よもや{f816}逃{f817}に{f818}げなどするまいな?{f801}{f802}{f816}貴様{f817}きさま{f818}らもアキュラの{f816}末裔{f817}まつえい{f818}ならば{f801}{f816}誇{f817}ほこ{f818}り{f816}高{f817}たか{f818}く{f816}戦{f817}たたか{f818}い{f816}抜{f817}ぬ{f818}いてみせよ{f801}{f802}</source>
    <target>{f871}{0100}…サムライどもよ{f801}よもや{f816}逃{f817}に{f818}げなどするまいな?{f801}{f802}{f816}貴様{f817}きさま{f818}らもアキュラの{f816}末裔{f817}まつえい{f818}ならば{f801}{f816}誇{f817}ほこ{f818}り{f816}高{f817}たか{f818}く{f816}戦{f817}たたか{f818}い{f816}抜{f817}ぬ{f818}いてみせよ{f801}{f802}</target>
  </entry>
  <entry id="6">
    <source>{f871}{0100}NOT USED{f801}{f802}</source>
    <target>{f871}{0100}NOT USED{f801}{f802}</target>
  </entry>
  <entry id="7">
    <source>NOT USED{f801}</source>
    <target>NOT USED{f801}</target>
  </entry>
  <entry id="8">
    <source>{f871}{0100}NOT USED{f801}{f802}</source>
    <target>{f871}{0100}NOT USED{f801}{f802}</target>
  </entry>
  <entry id="9">
    <source>NOT USED{f801}</source>
    <target>NOT USED{f801}</target>
  </entry>
  <entry id="10">
    <source>{f871}{0100}NOT USED{f801}{f802}</source>
    <target>{f871}{0100}NOT USED{f801}{f802}</target>
  </entry>
  <entry id="11">
    <source>NOT USED{f801}</source>
    <target>NOT USED{f801}</target>
  </entry>
  <entry id="12">
    <source>{f871}{0100}NOT USED{f801}{f802}</source>
    <target>{f871}{0100}NOT USED{f801}{f802}</target>
  </entry>
  <entry id="13">
    <source>{f871}{0100}NOT USED{f801}{f802}</source>
    <target>{f871}{0100}NOT USED{f801}{f802}</target>
  </entry>
  <entry id="14">
    <source>{f871}{0100}NOT USED{f801}{f802}</source>
    <target>{f871}{0100}NOT USED{f801}{f802}</target>
  </entry>
  <entry id="15">
    <source>{f871}{0100}NOT USED{f801}{f802}</source>
    <target>{f871}{0100}NOT USED{f801}{f802}</target>
  </entry>
  <entry id="16">
    <source>{f871}{0100}NOT USED{f801}{f802}</source>
    <target>{f871}{0100}NOT USED{f801}{f802}</target>
  </entry>
  <entry id="17">
    <source>{f871}{0100}NOT USED{f801}{f802}</source>
    <target>{f871}{0100}NOT USED{f801}{f802}</target>
  </entry>
  <entry id="18">
    <source>{f871}{0100}NOT USED{f801}{f802}</source>
    <target>{f871}{0100}NOT USED{f801}{f802}</target>
  </entry>
  <entry id="19">
    <source>{f871}{0100}NOT USED{f801}{f802}</source>
    <target>{f871}{0100}NOT USED{f801}{f802}</target>
  </entry>
  <entry id="20">
    <source>{f871}{0100}NOT USED{f801}{f802}</source>
    <target>{f871}{0100}NOT USED{f801}{f802}</target>
  </entry>
  <entry id="21">
    <source>{f871}{0100}NOT USED{f801}{f802}</source>
    <target>{f871}{0100}NOT USED{f801}{f802}</target>
  </entry>
  <entry id="22">
    <source>{f871}{0100}NOT USED{f801}{f802}</source>
    <target>{f871}{0100}NOT USED{f801}{f802}</target>
  </entry>
  <entry id="23">
    <source>NOT USED{f801}</source>
    <target>NOT USED{f801}</target>
  </entry>
  <entry id="24">
    <source>NOT USED{f801}</source>
    <target>NOT USED{f801}</target>
  </entry>
  <entry id="25">
    <source>{f871}{0100}NOT USED{f801}{f802}</source>
    <target>{f871}{0100}NOT USED{f801}{f802}</target>
  </entry>
  <entry id="26">
    <source>NOT USED{f801}</source>
    <target>NOT USED{f801}</target>
  </entry>
  <entry id="27">
    <source>{f871}{0100}NOT USED{f801}{f802}</source>
    <target>{f871}{0100}NOT USED{f801}{f802}</target>
  </entry>
  <entry id="28">
    <source>NOT USED{f801}</source>
    <target>NOT USED{f801}</target>
  </entry>
  <entry id="29">
    <source>{f871}{0100}NOT USED{f801}{f802}</source>
    <target>{f871}{0100}NOT USED{f801}{f802}</target>
  </entry>
  <entry id="30">
    <source>NOT USED{f801}</source>
    <target>NOT USED{f801}</target>
  </entry>
  <entry id="31">
    <source>NOT USED{f801}</source>
    <target>NOT USED{f801}</target>
  </entry>
  <entry id="32">
    <source>{f871}{0100}NOT USED{f801}{f802}</source>
    <target>{f871}{0100}NOT USED{f801}{f802}</target>
  </entry>
  <entry id="33">
    <source>NOT USED{f801}</source>
    <target>NOT USED{f801}</target>
  </entry>
  <entry id="34">
    <source>{f871}{0100}ナラクの{f816}深奥{f817}しんおう{f818}まで{f816}来{f817}き{f818}て{f801}ムダ{f816}話{f817}ばなし{f818}とは いかなるつもりか?{f801}{f802}{f816}何{f817}なん{f818}にせよ {f816}捧{f817}ささ{f818}げ{f816}物{f817}もの{f818}をしてもらうぞ{f801}{f802}</source>
    <target>{f871}{0100}ナラクの{f816}深奥{f817}しんおう{f818}まで{f816}来{f817}き{f818}て{f801}ムダ{f816}話{f817}ばなし{f818}とは いかなるつもりか?{f801}{f802}{f816}何{f817}なん{f818}にせよ {f816}捧{f817}ささ{f818}げ{f816}物{f817}もの{f818}をしてもらうぞ{f801}{f802}</target>
  </entry>
  <entry id="35">
    <source>NOT USED{f801}</source>
    <target>NOT USED{f801}</target>
  </entry>
  <entry id="36">
    <source>{f871}{0100}まあ{f816}良{f817}よ{f818}い ひとつサムライ{f816}相手{f817}あいて{f818}に{f801}{f816}語{f817}かた{f818}りでもしてやるか{f801}{f802}</source>
    <target>{f871}{0100}まあ{f816}良{f817}よ{f818}い ひとつサムライ{f816}相手{f817}あいて{f818}に{f801}{f816}語{f817}かた{f818}りでもしてやるか{f801}{f802}</target>
  </entry>
  <entry id="37">
    <source>NOT USED{f801}</source>
    <target>NOT USED{f801}</target>
  </entry>
  <entry id="38">
    <source>{f871}{0100}ガハハハ…ッ {f816}結構{f817}けっこう{f818} {f816}結構{f817}けっこう{f818}ッ{f801}サムライと{f816}語{f817}かた{f818}らおうぞッ!{f801}{f802}</source>
    <target>{f871}{0100}ガハハハ…ッ {f816}結構{f817}けっこう{f818} {f816}結構{f817}けっこう{f818}ッ{f801}サムライと{f816}語{f817}かた{f818}らおうぞッ!{f801}{f802}</target>
  </entry>
  <entry id="39">
    <source>NOT USED{f801}</source>
    <target>NOT USED{f801}</target>
  </entry>
  <entry id="40">
    <source>{f871}{0100}むう ついつい{f816}語{f817}かた{f818}りが{f816}弾{f817}はず{f818}むわ!{f801}ここで{f816}過{f817}す{f818}ごした{f816}時{f817}とき{f818}の{f816}長{f817}なが{f818}さゆえか…{f801}{f802}</source>
    <target>{f871}{0100}むう ついつい{f816}語{f817}かた{f818}りが{f816}弾{f817}はず{f818}むわ!{f801}ここで{f816}過{f817}す{f818}ごした{f816}時{f817}とき{f818}の{f816}長{f817}なが{f818}さゆえか…{f801}{f802}</target>
  </entry>
  <entry id="41">
    <source>NOT USED{f801}</source>
    <target>NOT USED{f801}</target>
  </entry>
  <entry id="42">
    <source>{f871}{0100}{f816}悪魔{f817}あくま{f818}に{f816}慈悲{f817}じひ{f818}を{f816}求{f817}もと{f818}めるか…{f801}{f816}弱{f817}よわ{f818}き{f816}者{f817}もの{f818} {f816}人{f817}ひと{f818}の{f816}子{f817}こ{f818}よ{f801}{f802}…ならば {f816}我{f817}われ{f818}に{f816}捧{f817}ささ{f818}げ{f816}物{f817}もの{f818}をせよ{f801}{f802}</source>
    <target>{f871}{0100}{f816}悪魔{f817}あくま{f818}に{f816}慈悲{f817}じひ{f818}を{f816}求{f817}もと{f818}めるか…{f801}{f816}弱{f817}よわ{f818}き{f816}者{f817}もの{f818} {f816}人{f817}ひと{f818}の{f816}子{f817}こ{f818}よ{f801}{f802}…ならば {f816}我{f817}われ{f818}に{f816}捧{f817}ささ{f818}げ{f816}物{f817}もの{f818}をせよ{f801}{f802}</target>
  </entry>
  <entry id="43">
    <source>NOT USED{f801}</source>
    <target>NOT USED{f801}</target>
  </entry>
  <entry id="44">
    <source>{f871}{0100}…{f816}捧{f817}ささ{f818}げ{f816}物{f817}もの{f818}に{f816}免{f817}めん{f818}じ{f801}{f816}特別{f817}とくべつ{f818}の{f816}慈悲{f817}じひ{f818}をくれてやろう{f801}{f802}</source>
    <target>{f871}{0100}…{f816}捧{f817}ささ{f818}げ{f816}物{f817}もの{f818}に{f816}免{f817}めん{f818}じ{f801}{f816}特別{f817}とくべつ{f818}の{f816}慈悲{f817}じひ{f818}をくれてやろう{f801}{f802}</target>
  </entry>
  <entry id="45">
    <source>NOT USED{f801}</source>
    <target>NOT USED{f801}</target>
  </entry>
  <entry id="46">
    <source>{f871}{0100}{f816}我{f817}われ{f818}は まどろみ…{f801}{f816}安息{f817}あんそく{f818}と {f816}慈悲{f817}じひ{f818}の これは{f816}眠{f817}ねむ{f818}り…{f801}{f802}{f816}慈悲{f817}じひ{f818}が{f816}欲{f817}ほ{f818}しくば くれてやる…{f801}{f802}</source>
    <target>{f871}{0100}{f816}我{f817}われ{f818}は まどろみ…{f801}{f816}安息{f817}あんそく{f818}と {f816}慈悲{f817}じひ{f818}の これは{f816}眠{f817}ねむ{f818}り…{f801}{f802}{f816}慈悲{f817}じひ{f818}が{f816}欲{f817}ほ{f818}しくば くれてやる…{f801}{f802}</target>
  </entry>
  <entry id="47">
    <source>NOT USED{f801}</source>
    <target>NOT USED{f801}</target>
  </entry>
  <entry id="48">
    <source>NOT USED{f801}</source>
    <target>NOT USED{f801}</target>
  </entry>
  <entry id="49">
    <source>{f871}{0100}ほう {f816}慈悲{f817}じひ{f818}の{f816}心地良{f817}ここちよ{f818}さよ{f801}どれ もう1{f816}度{f817}ど{f818}だ{f801}{f802}</source>
    <target>{f871}{0100}ほう {f816}慈悲{f817}じひ{f818}の{f816}心地良{f817}ここちよ{f818}さよ{f801}どれ もう1{f816}度{f817}ど{f818}だ{f801}{f802}</target>
  </entry>
  <entry id="50">
    <source>NOT USED{f801}</source>
    <target>NOT USED{f801}</target>
  </entry>
  <entry id="51">
    <source>{f871}{0100}…{f816}資金{f817}しきん{f818}を{f816}提供{f817}ていきょう{f818}してほしくて{f801}ナラクの{f816}深奥{f817}しんおう{f818}に{f816}来{f817}き{f818}たわけでもあるまい{f801}{f802}{f816}貴様{f817}きさま{f818} {f816}一体{f817}いったい{f818}どういうつもりで…{f801}{f802}</source>
    <target>{f871}{0100}…{f816}資金{f817}しきん{f818}を{f816}提供{f817}ていきょう{f818}してほしくて{f801}ナラクの{f816}深奥{f817}しんおう{f818}に{f816}来{f817}き{f818}たわけでもあるまい{f801}{f802}{f816}貴様{f817}きさま{f818} {f816}一体{f817}いったい{f818}どういうつもりで…{f801}{f802}</target>
  </entry>
  <entry id="52">
    <source>NOT USED{f801}</source>
    <target>NOT USED{f801}</target>
  </entry>
  <entry id="53">
    <source>{f871}{0100}サムライよ…{f801}{f816}金{f817}かね{f818}の{f816}欲{f817}よく{f818}に{f816}溺{f817}おぼ{f818}れたというのか…ッ{f801}{f802}</source>
    <target>{f871}{0100}サムライよ…{f801}{f816}金{f817}かね{f818}の{f816}欲{f817}よく{f818}に{f816}溺{f817}おぼ{f818}れたというのか…ッ{f801}{f802}</target>
  </entry>
  <entry id="54">
    <source>NOT USED{f801}</source>
    <target>NOT USED{f801}</target>
  </entry>
  <entry id="55">
    <source>{f871}{0100}{f816}金{f817}かね{f818}の{f816}欲{f817}よく{f818}に{f816}溺{f817}おぼ{f818}れ {f816}分別{f817}ふんべつ{f818}を{f816}見失{f817}みうしな{f818}い{f801}サムライとして {f816}何{f817}なん{f818}と{f816}醜{f817}みにく{f818}き{f816}姿{f817}すがた{f818}よ{f801}{f802}{f816}貴様{f817}きさま{f818}こそは {f816}外道{f817}げどう{f818}のサムライとして{f801}ここに{f816}屍{f817}しかばね{f818}をさらすべし!{f801}{f802}</source>
    <target>{f871}{0100}{f816}金{f817}かね{f818}の{f816}欲{f817}よく{f818}に{f816}溺{f817}おぼ{f818}れ {f816}分別{f817}ふんべつ{f818}を{f816}見失{f817}みうしな{f818}い{f801}サムライとして {f816}何{f817}なん{f818}と{f816}醜{f817}みにく{f818}き{f816}姿{f817}すがた{f818}よ{f801}{f802}{f816}貴様{f817}きさま{f818}こそは {f816}外道{f817}げどう{f818}のサムライとして{f801}ここに{f816}屍{f817}しかばね{f818}をさらすべし!{f801}{f802}</target>
  </entry>
  <entry id="56">
    <source>NOT USED{f801}</source>
    <target>NOT USED{f801}</target>
  </entry>
  <entry id="57">
    <source>{f871}{0100}ぐほッ よさぬかー!{f801}{f802}</source>
    <target>{f871}{0100}ぐほッ よさぬかー!{f801}{f802}</target>
  </entry>
  <entry id="58">
    <source>NOT USED{f801}</source>
    <target>NOT USED{f801}</target>
  </entry>
  <entry id="59">
    <source>{f871}{0100}き {f816}貴様{f817}きさま{f818}…ッ{f801}やめるなら {f816}今{f817}いま{f818}のうちだぞ…{f801}{f802}</source>
    <target>{f871}{0100}き {f816}貴様{f817}きさま{f818}…ッ{f801}やめるなら {f816}今{f817}いま{f818}のうちだぞ…{f801}{f802}</target>
  </entry>
  <entry id="60">
    <source>NOT USED{f801}</source>
    <target>NOT USED{f801}</target>
  </entry>
  <entry id="61">
    <source>{f871}{0100}うおぉぉぉーッ{f801}そんなに{f816}金{f817}かね{f818}が{f816}欲{f817}ほ{f818}しいならば!{f801}{f802}ほれ すべて{f816}持{f817}も{f818}っていけッ!{f801}そして{f816}失{f817}う{f818}せろ!{f801}{f802}</source>
    <target>{f871}{0100}うおぉぉぉーッ{f801}そんなに{f816}金{f817}かね{f818}が{f816}欲{f817}ほ{f818}しいならば!{f801}{f802}ほれ すべて{f816}持{f817}も{f818}っていけッ!{f801}そして{f816}失{f817}う{f818}せろ!{f801}{f802}</target>
  </entry>
  <entry id="62">
    <source>NOT USED{f801}</source>
    <target>NOT USED{f801}</target>
  </entry>
  <entry id="63">
    <source>{f871}{0100}ふはははははは…{f801}はーはははははは…ッ{f801}{f802}{f816}遊{f817}あそ{f818}びは{f816}仕舞{f817}しま{f818}いだッ{f801}{f802}</source>
    <target>{f871}{0100}ふはははははは…{f801}はーはははははは…ッ{f801}{f802}{f816}遊{f817}あそ{f818}びは{f816}仕舞{f817}しま{f818}いだッ{f801}{f802}</target>
  </entry>
  <entry id="64">
    <source>NOT USED{f801}</source>
    <target>NOT USED{f801}</target>
  </entry>
  <entry id="65">
    <source>{f871}{0100}…{f816}資金{f817}しきん{f818}を{f816}提供{f817}ていきょう{f818}してほしくて{f801}ナラクの{f816}深奥{f817}しんおう{f818}に{f816}来{f817}き{f818}たわけでもあるまい{f801}{f802}{f816}貴様{f817}きさま{f818} {f816}一体{f817}いったい{f818}どういうつもりで…{f801}{f802}</source>
    <target>{f871}{0100}…{f816}資金{f817}しきん{f818}を{f816}提供{f817}ていきょう{f818}してほしくて{f801}ナラクの{f816}深奥{f817}しんおう{f818}に{f816}来{f817}き{f818}たわけでもあるまい{f801}{f802}{f816}貴様{f817}きさま{f818} {f816}一体{f817}いったい{f818}どういうつもりで…{f801}{f802}</target>
  </entry>
  <entry id="66">
    <source>NOT USED{f801}</source>
    <target>NOT USED{f801}</target>
  </entry>
  <entry id="67">
    <source>{f871}{0100}{f816}商談{f817}しょうだん{f818}…というわけか{f801}よかろう {f816}対価{f817}たいか{f818}さえ{f816}払{f817}はら{f818}えばな{f801}{f802}</source>
    <target>{f871}{0100}{f816}商談{f817}しょうだん{f818}…というわけか{f801}よかろう {f816}対価{f817}たいか{f818}さえ{f816}払{f817}はら{f818}えばな{f801}{f802}</target>
  </entry>
  <entry id="68">
    <source>NOT USED{f801}</source>
    <target>NOT USED{f801}</target>
  </entry>
  <entry id="69">
    <source>{f871}{0100}{f816}商談{f817}しょうだん{f818}は{f816}成立{f817}せいりつ{f818}だ{f801}この{f816}品{f817}しな{f818}にて {f816}報{f817}むく{f818}いてやろう{f801}{f802}</source>
    <target>{f871}{0100}{f816}商談{f817}しょうだん{f818}は{f816}成立{f817}せいりつ{f818}だ{f801}この{f816}品{f817}しな{f818}にて {f816}報{f817}むく{f818}いてやろう{f801}{f802}</target>
  </entry>
  <entry id="70">
    <source>NOT USED{f801}</source>
    <target>NOT USED{f801}</target>
  </entry>
  <entry id="71">
    <source>{f871}{0100}{f816}我{f817}われ{f818}の{f816}秘蔵{f817}ひぞう{f818}の{f816}品{f817}しな{f818}か{f801}ふはははッ くれてやるわ!{f801}{f802}こんなものを{f816}惜{f817}お{f818}しんで {f816}何{f817}なに{f818}が{f816}悪魔{f817}あくま{f818}ぞッ{f801}ほーれ {f816}持{f817}も{f818}っていけー{f801}{f802}</source>
    <target>{f871}{0100}{f816}我{f817}われ{f818}の{f816}秘蔵{f817}ひぞう{f818}の{f816}品{f817}しな{f818}か{f801}ふはははッ くれてやるわ!{f801}{f802}こんなものを{f816}惜{f817}お{f818}しんで {f816}何{f817}なに{f818}が{f816}悪魔{f817}あくま{f818}ぞッ{f801}ほーれ {f816}持{f817}も{f818}っていけー{f801}{f802}</target>
  </entry>
  <entry id="72">
    <source>NOT USED{f801}</source>
    <target>NOT USED{f801}</target>
  </entry>
  <entry id="73">
    <source>{f871}{0100}…ついでだ これもくれてやる{f801}{f816}我{f817}われ{f818}には{f816}無用{f817}むよう{f818}のものだ{f801}{f802}</source>
    <target>{f871}{0100}…ついでだ これもくれてやる{f801}{f816}我{f817}われ{f818}には{f816}無用{f817}むよう{f818}のものだ{f801}{f802}</target>
  </entry>
  <entry id="74">
    <source>NOT USED{f801}</source>
    <target>NOT USED{f801}</target>
  </entry>
  <entry id="75">
    <source>{f871}{0100}…{f816}時間{f817}じかん{f818}が{f816}惜{f817}お{f818}しい{f801}{f816}即決{f817}そっけつ{f818}にて {f816}話{f817}はなし{f818}を{f816}付{f817}つ{f818}ける{f801}{f802}{f804}{0100}{f878}{0100}マッカ{f804}{0000}…{f801}{f816}貴様{f817}きさま{f818}に{f816}出{f817}だ{f818}せるか?{f801}{f802}</source>
    <target>{f871}{0100}…{f816}時間{f817}じかん{f818}が{f816}惜{f817}お{f818}しい{f801}{f816}即決{f817}そっけつ{f818}にて {f816}話{f817}はなし{f818}を{f816}付{f817}つ{f818}ける{f801}{f802}{f804}{0100}{f878}{0100}マッカ{f804}{0000}…{f801}{f816}貴様{f817}きさま{f818}に{f816}出{f817}だ{f818}せるか?{f801}{f802}</target>
  </entry>
  <entry id="76">
    <source>NOT USED{f801}</source>
    <target>NOT USED{f801}</target>
  </entry>
  <entry id="77">
    <source>{f871}{0100}{f804}{0100}{f872}{0100}{f804}{0000}を{f816}貰{f817}もら{f818}おうか{f801}{f802}</source>
    <target>{f871}{0100}{f804}{0100}{f872}{0100}{f804}{0000}を{f816}貰{f817}もら{f818}おうか{f801}{f802}</target>
  </entry>
  <entry id="78">
    <source>NOT USED{f801}</source>
    <target>NOT USED{f801}</target>
  </entry>
  <entry id="79">
    <source>{f871}{0100}{f804}{0100}{f878}{0100}マッカ{f804}{0000}{f816}貰{f817}もら{f818}おうか{f801}{f802}</source>
    <target>{f871}{0100}{f804}{0100}{f878}{0100}マッカ{f804}{0000}{f816}貰{f817}もら{f818}おうか{f801}{f802}</target>
  </entry>
  <entry id="80">
    <source>NOT USED{f801}</source>
    <target>NOT USED{f801}</target>
  </entry>
  <entry id="81">
    <source>{f871}{0100}{f816}貴様{f817}きさま{f818}の{f804}{0100}{f816}生命力{f817}せいめいりょく{f818}{f804}{0000}を{f801}{f804}{0100}{f816}少々{f817}しょうしょう{f818}{f804}{0000} {f816}頂{f817}いただ{f818}こう{f801}{f802}</source>
    <target>{f871}{0100}{f816}貴様{f817}きさま{f818}の{f804}{0100}{f816}生命力{f817}せいめいりょく{f818}{f804}{0000}を{f801}{f804}{0100}{f816}少々{f817}しょうしょう{f818}{f804}{0000} {f816}頂{f817}いただ{f818}こう{f801}{f802}</target>
  </entry>
  <entry id="82">
    <source>NOT USED{f801}</source>
    <target>NOT USED{f801}</target>
  </entry>
  <entry id="83">
    <source>{f871}{0100}{f816}貴様{f817}きさま{f818}の{f804}{0100}{f816}生命力{f817}せいめいりょく{f818}{f804}{0000}を{f801}{f804}{0100}そこそこ{f804}{0000} {f816}頂{f817}いただ{f818}こう{f801}{f802}</source>
    <target>{f871}{0100}{f816}貴様{f817}きさま{f818}の{f804}{0100}{f816}生命力{f817}せいめいりょく{f818}{f804}{0000}を{f801}{f804}{0100}そこそこ{f804}{0000} {f816}頂{f817}いただ{f818}こう{f801}{f802}</target>
  </entry>
  <entry id="84">
    <source>NOT USED{f801}</source>
    <target>NOT USED{f801}</target>
  </entry>
  <entry id="85">
    <source>{f871}{0100}{f816}貴様{f817}きさま{f818}の{f804}{0100}{f816}生命力{f817}せいめいりょく{f818}{f804}{0000}を{f801}{f804}{0100}{f816}相当{f817}そうとう{f818}に{f804}{0000} {f816}頂{f817}いただ{f818}こう{f801}{f802}</source>
    <target>{f871}{0100}{f816}貴様{f817}きさま{f818}の{f804}{0100}{f816}生命力{f817}せいめいりょく{f818}{f804}{0000}を{f801}{f804}{0100}{f816}相当{f817}そうとう{f818}に{f804}{0000} {f816}頂{f817}いただ{f818}こう{f801}{f802}</target>
  </entry>
  <entry id="86">
    <source>NOT USED{f801}</source>
    <target>NOT USED{f801}</target>
  </entry>
  <entry id="87">
    <source>{f871}{0100}{f816}貴様{f817}きさま{f818}の{f804}{0100}{f816}生命力{f817}せいめいりょく{f818}{f804}{0000}を{f801}{f804}{0100}{f816}恐{f817}おそ{f818}ろしいほど{f804}{0000} {f816}頂{f817}いただ{f818}こう{f801}{f802}</source>
    <target>{f871}{0100}{f816}貴様{f817}きさま{f818}の{f804}{0100}{f816}生命力{f817}せいめいりょく{f818}{f804}{0000}を{f801}{f804}{0100}{f816}恐{f817}おそ{f818}ろしいほど{f804}{0000} {f816}頂{f817}いただ{f818}こう{f801}{f802}</target>
  </entry>
  <entry id="88">
    <source>NOT USED{f801}</source>
    <target>NOT USED{f801}</target>
  </entry>
  <entry id="89">
    <source>{f871}{0100}{f816}貴様{f817}きさま{f818}の{f804}{0100}{f816}精神力{f817}せいしんりょく{f818}{f804}{0000}を{f801}{f804}{0100}{f816}少々{f817}しょうしょう{f818}{f804}{0000} {f816}頂{f817}いただ{f818}こう{f801}{f802}</source>
    <target>{f871}{0100}{f816}貴様{f817}きさま{f818}の{f804}{0100}{f816}精神力{f817}せいしんりょく{f818}{f804}{0000}を{f801}{f804}{0100}{f816}少々{f817}しょうしょう{f818}{f804}{0000} {f816}頂{f817}いただ{f818}こう{f801}{f802}</target>
  </entry>
  <entry id="90">
    <source>NOT USED{f801}</source>
    <target>NOT USED{f801}</target>
  </entry>
  <entry id="91">
    <source>{f871}{0100}{f816}貴様{f817}きさま{f818}の{f804}{0100}{f816}精神力{f817}せいしんりょく{f818}{f804}{0000}を{f801}{f804}{0100}そこそこ{f804}{0000} {f816}頂{f817}いただ{f818}こう{f801}{f802}</source>
    <target>{f871}{0100}{f816}貴様{f817}きさま{f818}の{f804}{0100}{f816}精神力{f817}せいしんりょく{f818}{f804}{0000}を{f801}{f804}{0100}そこそこ{f804}{0000} {f816}頂{f817}いただ{f818}こう{f801}{f802}</target>
  </entry>
  <entry id="92">
    <source>NOT USED{f801}</source>
    <target>NOT USED{f801}</target>
  </entry>
  <entry id="93">
    <source>{f871}{0100}{f816}貴様{f817}きさま{f818}の{f804}{0100}{f816}精神力{f817}せいしんりょく{f818}{f804}{0000}を{f801}{f804}{0100}{f816}相当{f817}そうとう{f818}に{f804}{0000} {f816}頂{f817}いただ{f818}こう{f801}{f802}</source>
    <target>{f871}{0100}{f816}貴様{f817}きさま{f818}の{f804}{0100}{f816}精神力{f817}せいしんりょく{f818}{f804}{0000}を{f801}{f804}{0100}{f816}相当{f817}そうとう{f818}に{f804}{0000} {f816}頂{f817}いただ{f818}こう{f801}{f802}</target>
  </entry>
  <entry id="94">
    <source>NOT USED{f801}</source>
    <target>NOT USED{f801}</target>
  </entry>
  <entry id="95">
    <source>{f871}{0100}{f816}貴様{f817}きさま{f818}の{f804}{0100}{f816}精神力{f817}せいしんりょく{f818}{f804}{0000}を{f801}{f804}{0100}{f816}恐{f817}おそ{f818}ろしいほど{f804}{0000} {f816}頂{f817}いただ{f818}こう{f801}{f802}</source>
    <target>{f871}{0100}{f816}貴様{f817}きさま{f818}の{f804}{0100}{f816}精神力{f817}せいしんりょく{f818}{f804}{0000}を{f801}{f804}{0100}{f816}恐{f817}おそ{f818}ろしいほど{f804}{0000} {f816}頂{f817}いただ{f818}こう{f801}{f802}</target>
  </entry>
  <entry id="96">
    <source>NOT USED{f801}</source>
    <target>NOT USED{f801}</target>
  </entry>
  <entry id="97">
    <source>{f871}{0100}{f816}貴様{f817}きさま{f818}の{f816}仲魔{f817}なかま{f818}…{f801}{f804}{0100}{f873}{0200}の{f816}命{f817}いのち{f818}{f804}{0000}を{f816}貰{f817}もら{f818}おうか{f801}{f802}</source>
    <target>{f871}{0100}{f816}貴様{f817}きさま{f818}の{f816}仲魔{f817}なかま{f818}…{f801}{f804}{0100}{f873}{0200}の{f816}命{f817}いのち{f818}{f804}{0000}を{f816}貰{f817}もら{f818}おうか{f801}{f802}</target>
  </entry>
  <entry id="98">
    <source>NOT USED{f801}</source>
    <target>NOT USED{f801}</target>
  </entry>
  <entry id="99">
    <source>{f871}{0100}{f804}{0100}アレ{f804}{0000}だな…{f801}うむ…{f804}{0100}アレ{f804}{0000}だな…{f801}{f802}</source>
    <target>{f871}{0100}{f804}{0100}アレ{f804}{0000}だな…{f801}うむ…{f804}{0100}アレ{f804}{0000}だな…{f801}{f802}</target>
  </entry>
  <entry id="100">
    <source>NOT USED{f801}</source>
    <target>NOT USED{f801}</target>
  </entry>
  <entry id="101">
    <source>{f871}{0100}{f816}貴様{f817}きさま{f818} どれか{f816}選{f817}えら{f818}べ{f801}{f802}</source>
    <target>{f871}{0100}{f816}貴様{f817}きさま{f818} どれか{f816}選{f817}えら{f818}べ{f801}{f802}</target>
  </entry>
  <entry id="102">
    <source>NOT USED{f801}</source>
    <target>NOT USED{f801}</target>
  </entry>
  <entry id="103">
    <source>{f871}{0100}…うむ {f816}貰{f817}もら{f818}っておこう{f801}{f802}</source>
    <target>{f871}{0100}…うむ {f816}貰{f817}もら{f818}っておこう{f801}{f802}</target>
  </entry>
  <entry id="104">
    <source>NOT USED{f801}</source>
    <target>NOT USED{f801}</target>
  </entry>
  <entry id="105">
    <source>{f871}{0100}…{f816}違{f817}ちが{f818}うわ {f816}愚{f817}おろ{f818}か{f816}者{f817}もの{f818}め{f801}{f802}</source>
    <target>{f871}{0100}…{f816}違{f817}ちが{f818}うわ {f816}愚{f817}おろ{f818}か{f816}者{f817}もの{f818}め{f801}{f802}</target>
  </entry>
  <entry id="106">
    <source>NOT USED{f801}</source>
    <target>NOT USED{f801}</target>
  </entry>
  <entry id="107">
    <source>{f871}{0100}NOT USED{f801}{f802}</source>
    <target>{f871}{0100}NOT USED{f801}{f802}</target>
  </entry>
  <entry id="108">
    <source>NOT USED{f801}</source>
    <target>NOT USED{f801}</target>
  </entry>
  <entry id="109">
    <source>NOT USED{f801}{f802}</source>
    <target>NOT USED{f801}{f802}</target>
  </entry>
  <entry id="110">
    <source>{f871}{0100}NOT USED{f801}{f802}</source>
    <target>{f871}{0100}NOT USED{f801}{f802}</target>
  </entry>
  <entry id="111">
    <source>NOT USED{f801}</source>
    <target>NOT USED{f801}</target>
  </entry>
  <entry id="112">
    <source>NOT USED{f801}{f802}</source>
    <target>NOT USED{f801}{f802}</target>
  </entry>
  <entry id="113">
    <source>NOT USED{f801}{f802}</source>
    <target>NOT USED{f801}{f802}</target>
  </entry>
  <entry id="114">
    <source>{f871}{0100}NOT USED{f801}{f802}</source>
    <target>{f871}{0100}NOT USED{f801}{f802}</target>
  </entry>
  <entry id="115">
    <source>NOT USED{f801}</source>
    <target>NOT USED{f801}</target>
  </entry>
  <entry id="116">
    <source>NOT USED{f801}{f802}</source>
    <target>NOT USED{f801}{f802}</target>
  </entry>
  <entry id="117">
    <source>NOT USED{f801}{f802}</source>
    <target>NOT USED{f801}{f802}</target>
  </entry>
  <entry id="118">
    <source>{f871}{0100}NOT USED{f801}{f802}</source>
    <target>{f871}{0100}NOT USED{f801}{f802}</target>
  </entry>
  <entry id="119">
    <source>NOT USED{f801}</source>
    <target>NOT USED{f801}</target>
  </entry>
  <entry id="120">
    <source>{f871}{0100}…うむ {f816}我{f817}われ{f818}は{f816}満足{f817}まんぞく{f818}だ{f801}{f802}</source>
    <target>{f871}{0100}…うむ {f816}我{f817}われ{f818}は{f816}満足{f817}まんぞく{f818}だ{f801}{f802}</target>
  </entry>
  <entry id="121">
    <source>NOT USED{f801}</source>
    <target>NOT USED{f801}</target>
  </entry>
  <entry id="122">
    <source>{f871}{0100}ふむぅ! これはたまらん…ッ{f801}{f802}</source>
    <target>{f871}{0100}ふむぅ! これはたまらん…ッ{f801}{f802}</target>
  </entry>
  <entry id="123">
    <source>NOT USED{f801}</source>
    <target>NOT USED{f801}</target>
  </entry>
  <entry id="124">
    <source>{f871}{0100}ほう そう{f816}来{f817}き{f818}たか…{f801}{f802}</source>
    <target>{f871}{0100}ほう そう{f816}来{f817}き{f818}たか…{f801}{f802}</target>
  </entry>
  <entry id="125">
    <source>NOT USED{f801}</source>
    <target>NOT USED{f801}</target>
  </entry>
  <entry id="126">
    <source>{f871}{0100}{f816}持{f817}も{f818}っているのに よこさぬと{f801}それが{f816}貴様{f817}きさま{f818}の{f816}答{f817}こた{f818}えか…{f801}{f802}ならば {f816}死{f817}し{f818}をもって{f816}報{f817}むく{f818}いよ…ッ{f801}{f802}</source>
    <target>{f871}{0100}{f816}持{f817}も{f818}っているのに よこさぬと{f801}それが{f816}貴様{f817}きさま{f818}の{f816}答{f817}こた{f818}えか…{f801}{f802}ならば {f816}死{f817}し{f818}をもって{f816}報{f817}むく{f818}いよ…ッ{f801}{f802}</target>
  </entry>
  <entry id="127">
    <source>NOT USED{f801}</source>
    <target>NOT USED{f801}</target>
  </entry>
  <entry id="128">
    <source>{f871}{0100}{f816}分{f817}わ{f818}かった もう{f816}結構{f817}けっこう{f818}だ{f801}{f802}</source>
    <target>{f871}{0100}{f816}分{f817}わ{f818}かった もう{f816}結構{f817}けっこう{f818}だ{f801}{f802}</target>
  </entry>
  <entry id="129">
    <source>NOT USED{f801}</source>
    <target>NOT USED{f801}</target>
  </entry>
  <entry id="130">
    <source>{f871}{0100}{f816}貴様{f817}きさま{f818} ごまかしたな{f801}それが{f816}貴様{f817}きさま{f818}の{f816}答{f817}こた{f818}えか…{f801}{f802}ならば {f816}死{f817}し{f818}をもって{f816}報{f817}むく{f818}いよ…ッ{f801}{f802}</source>
    <target>{f871}{0100}{f816}貴様{f817}きさま{f818} ごまかしたな{f801}それが{f816}貴様{f817}きさま{f818}の{f816}答{f817}こた{f818}えか…{f801}{f802}ならば {f816}死{f817}し{f818}をもって{f816}報{f817}むく{f818}いよ…ッ{f801}{f802}</target>
  </entry>
  <entry id="131">
    <source>NOT USED{f801}</source>
    <target>NOT USED{f801}</target>
  </entry>
  <entry id="132">
    <source>{f871}{0100}…{f816}役立{f817}やくた{f818}たずめ{f801}{f802}</source>
    <target>{f871}{0100}…{f816}役立{f817}やくた{f818}たずめ{f801}{f802}</target>
  </entry>
  <entry id="133">
    <source>NOT USED{f801}</source>
    <target>NOT USED{f801}</target>
  </entry>
  <entry id="134">
    <source>{f871}{0100}{f816}魔石{f817}ませき{f818}なくしては {f816}始{f817}はじ{f818}まらぬ…{f801}{f802}</source>
    <target>{f871}{0100}{f816}魔石{f817}ませき{f818}なくしては {f816}始{f817}はじ{f818}まらぬ…{f801}{f802}</target>
  </entry>
  <entry id="135">
    <source>NOT USED{f801}</source>
    <target>NOT USED{f801}</target>
  </entry>
  <entry id="136">
    <source>{f871}{0100}…{f816}少々{f817}しょうしょう{f818} {f816}長{f817}なが{f818}かったか{f801}{f816}我{f817}われ{f818}としたことが {f816}無粋{f817}ぶすい{f818}だな{f801}{f802}</source>
    <target>{f871}{0100}…{f816}少々{f817}しょうしょう{f818} {f816}長{f817}なが{f818}かったか{f801}{f816}我{f817}われ{f818}としたことが {f816}無粋{f817}ぶすい{f818}だな{f801}{f802}</target>
  </entry>
  <entry id="137">
    <source>NOT USED{f801}</source>
    <target>NOT USED{f801}</target>
  </entry>
  <entry id="138">
    <source>{f871}{0100}{f816}我{f817}われ{f818}には{f816}付{f817}つ{f818}き{f816}合{f817}あ{f818}えぬとな{f801}それが{f816}貴様{f817}きさま{f818}の{f816}答{f817}こた{f818}えか…{f801}{f802}ならば {f816}死{f817}し{f818}をもって{f816}報{f817}むく{f818}いよ…ッ{f801}{f802}</source>
    <target>{f871}{0100}{f816}我{f817}われ{f818}には{f816}付{f817}つ{f818}き{f816}合{f817}あ{f818}えぬとな{f801}それが{f816}貴様{f817}きさま{f818}の{f816}答{f817}こた{f818}えか…{f801}{f802}ならば {f816}死{f817}し{f818}をもって{f816}報{f817}むく{f818}いよ…ッ{f801}{f802}</target>
  </entry>
  <entry id="139">
    <source>NOT USED{f801}</source>
    <target>NOT USED{f801}</target>
  </entry>
  <entry id="140">
    <source>{f871}{0100}この{f816}我{f817}われ{f818}に{f816}向{f817}む{f818}かって{f801}かくも{f816}頑{f817}かたく{f818}なに{f816}拒{f817}こば{f818}み{f816}続{f817}つづ{f818}けるか…{f801}{f802}…いいぞッ {f816}実{f817}じつ{f818}に{f816}面白{f817}おもしろ{f818}い!{f801}{f802}</source>
    <target>{f871}{0100}この{f816}我{f817}われ{f818}に{f816}向{f817}む{f818}かって{f801}かくも{f816}頑{f817}かたく{f818}なに{f816}拒{f817}こば{f818}み{f816}続{f817}つづ{f818}けるか…{f801}{f802}…いいぞッ {f816}実{f817}じつ{f818}に{f816}面白{f817}おもしろ{f818}い!{f801}{f802}</target>
  </entry>
  <entry id="141">
    <source>NOT USED{f801}</source>
    <target>NOT USED{f801}</target>
  </entry>
  <entry id="142">
    <source>{f871}{0100}{f816}先程{f817}さきほど{f818}から{f816}応{f817}おう{f818}じてばかりだな{f801}{f816}貴様{f817}きさま{f818} {f816}物言{f817}ものい{f818}う{f816}口{f817}くち{f818}を{f816}持{f817}も{f818}たぬのか?{f801}{f802}…もういい {f816}失{f817}う{f818}せろ{f801}{f802}</source>
    <target>{f871}{0100}{f816}先程{f817}さきほど{f818}から{f816}応{f817}おう{f818}じてばかりだな{f801}{f816}貴様{f817}きさま{f818} {f816}物言{f817}ものい{f818}う{f816}口{f817}くち{f818}を{f816}持{f817}も{f818}たぬのか?{f801}{f802}…もういい {f816}失{f817}う{f818}せろ{f801}{f802}</target>
  </entry>
  <entry id="143">
    <source>NOT USED{f801}</source>
    <target>NOT USED{f801}</target>
  </entry>
  <entry id="144">
    <source>{f871}{0100}ふはははは…ッ{f801}{f816}哀{f817}あわ{f818}れだな {f816}持{f817}も{f818}たざる{f816}者{f817}もの{f818}よ!{f801}{f802}</source>
    <target>{f871}{0100}ふはははは…ッ{f801}{f816}哀{f817}あわ{f818}れだな {f816}持{f817}も{f818}たざる{f816}者{f817}もの{f818}よ!{f801}{f802}</target>
  </entry>
  <entry id="145">
    <source>NOT USED{f801}</source>
    <target>NOT USED{f801}</target>
  </entry>
  <entry id="146">
    <source>{f871}{0100}NOT USED{f801}{f802}</source>
    <target>{f871}{0100}NOT USED{f801}{f802}</target>
  </entry>
  <entry id="147">
    <source>NOT USED{f801}</source>
    <target>NOT USED{f801}</target>
  </entry>
  <entry id="148">
    <source>{f871}{0100}NOT USED{f801}{f802}</source>
    <target>{f871}{0100}NOT USED{f801}{f802}</target>
  </entry>
  <entry id="149">
    <source>NOT USED{f801}</source>
    <target>NOT USED{f801}</target>
  </entry>
  <entry id="150">
    <source>{f871}{0100}NOT USED{f801}{f802}</source>
    <target>{f871}{0100}NOT USED{f801}{f802}</target>
  </entry>
  <entry id="151">
    <source>NOT USED{f801}</source>
    <target>NOT USED{f801}</target>
  </entry>
  <entry id="152">
    <source>{f871}{0100}NOT USED{f801}{f802}</source>
    <target>{f871}{0100}NOT USED{f801}{f802}</target>
  </entry>
  <entry id="153">
    <source>NOT USED{f801}</source>
    <target>NOT USED{f801}</target>
  </entry>
  <entry id="154">
    <source>{f871}{0100}NOT USED{f801}{f802}</source>
    <target>{f871}{0100}NOT USED{f801}{f802}</target>
  </entry>
  <entry id="155">
    <source>NOT USED{f801}</source>
    <target>NOT USED{f801}</target>
  </entry>
  <entry id="156">
    <source>{f871}{0100}NOT USED{f801}{f802}</source>
    <target>{f871}{0100}NOT USED{f801}{f802}</target>
  </entry>
  <entry id="157">
    <source>NOT USED{f801}</source>
    <target>NOT USED{f801}</target>
  </entry>
  <entry id="158">
    <source>{f871}{0100}NOT USED{f801}{f802}</source>
    <target>{f871}{0100}NOT USED{f801}{f802}</target>
  </entry>
  <entry id="159">
    <source>NOT USED{f801}</source>
    <target>NOT USED{f801}</target>
  </entry>
  <entry id="160">
    <source>{f871}{0100}NOT USED{f801}{f802}</source>
    <target>{f871}{0100}NOT USED{f801}{f802}</target>
  </entry>
  <entry id="161">
    <source>NOT USED{f801}</source>
    <target>NOT USED{f801}</target>
  </entry>
  <entry id="162">
    <source>{f871}{0100}またその{f816}話{f817}はなし{f818}か{f801}{f816}我{f817}われ{f818}を {f816}飽{f817}あ{f818}きさせるなよ…{f801}{f802}</source>
    <target>{f871}{0100}またその{f816}話{f817}はなし{f818}か{f801}{f816}我{f817}われ{f818}を {f816}飽{f817}あ{f818}きさせるなよ…{f801}{f802}</target>
  </entry>
  <entry id="163">
    <source>NOT USED{f801}</source>
    <target>NOT USED{f801}</target>
  </entry>
  <entry id="164">
    <source>{f871}{0100}{f816}我{f817}われ{f818}らが{f816}新{f817}あら{f818}たなる{f816}盟約{f817}めいやく{f818}は{f801}いかに{f816}離{f817}はな{f818}れようとも{f816}潰{f817}つい{f818}えはせぬ{f801}{f802}さあ {f816}往{f817}ゆ{f818}こうではないか{f801}{f816}我{f817}わ{f818}が{f816}主{f817}あるじ{f818} {f843}{0000}よ{f801}{f802}</source>
    <target>{f871}{0100}{f816}我{f817}われ{f818}らが{f816}新{f817}あら{f818}たなる{f816}盟約{f817}めいやく{f818}は{f801}いかに{f816}離{f817}はな{f818}れようとも{f816}潰{f817}つい{f818}えはせぬ{f801}{f802}さあ {f816}往{f817}ゆ{f818}こうではないか{f801}{f816}我{f817}わ{f818}が{f816}主{f817}あるじ{f818} {f843}{0000}よ{f801}{f802}</target>
  </entry>
  <entry id="165">
    <source>{f871}{0100}NOT USED{f801}{f802}</source>
    <target>{f871}{0100}NOT USED{f801}{f802}</target>
  </entry>
  <entry id="166">
    <source>NOT USED{f801}</source>
    <target>NOT USED{f801}</target>
  </entry>
  <entry id="167">
    <source>{f871}{0100}NOT USED{f801}{f802}</source>
    <target>{f871}{0100}NOT USED{f801}{f802}</target>
  </entry>
  <entry id="168">
    <source>NOT USED{f801}</source>
    <target>NOT USED{f801}</target>
  </entry>
  <entry id="169">
    <source>{f871}{0100}NOT USED{f801}{f802}</source>
    <target>{f871}{0100}NOT USED{f801}{f802}</target>
  </entry>
  <entry id="170">
    <source>NOT USED{f801}</source>
    <target>NOT USED{f801}</target>
  </entry>
  <entry id="171">
    <source>{f871}{0100}リザーブ{f801}{f802}</source>
    <target>{f871}{0100}リザーブ{f801}{f802}</target>
  </entry>
  <entry id="172">
    <source>{f871}{0100}リザーブ{f801}{f802}</source>
    <target>{f871}{0100}リザーブ{f801}{f802}</target>
  </entry>
  <entry id="173">
    <source>{f871}{0100}リザーブ{f801}{f802}</source>
    <target>{f871}{0100}リザーブ{f801}{f802}</target>
  </entry>
  <entry id="174">
    <source>{f871}{0100}リザーブ{f801}{f802}</source>
    <target>{f871}{0100}リザーブ{f801}{f802}</target>
  </entry>
</mbm>