<mbm>
  <entry id="0">
    <source>{f812}声{0000}{f87a}{2f00}{f813}{0000}{0000}{21bf}{0200}おっと {f816}待{f817}ま{f818}ちな{f801}</source>
    <target>{f812}声{0000}{f87a}{2f00}{f813}{0000}{0000}{21bf}{0200}おっと {f816}待{f817}ま{f818}ちな{f801}</target>
  </entry>
  <entry id="1">
    <source>{f812}阿修羅会の男{0000}{f87a}{8900}{f813}{0000}{0000}{22bf}{0200}…こっから{f816}先{f817}さき{f818}へは{f816}行{f817}い{f818}かせねぇよ{f801}</source>
    <target>{f812}阿修羅会の男{0000}{f87a}{8900}{f813}{0000}{0000}{22bf}{0200}…こっから{f816}先{f817}さき{f818}へは{f816}行{f817}い{f818}かせねぇよ{f801}</target>
  </entry>
  <entry id="2">
    <source>{f812}ワルター{0000}{f87a}{0400}{f813}{0000}{0000}{23bf}{0200}{f816}今{f817}いま{f818}さら{f816}下{f817}した{f818}っ{f816}端{f817}ぱ{f818}の{f816}出番{f817}でばん{f818}でもないだろうよ{f801}{f816}殺{f817}ころ{f818}されたくなかったら{f816}道{f817}みち{f818}をあけな{f801}</source>
    <target>{f812}ワルター{0000}{f87a}{0400}{f813}{0000}{0000}{23bf}{0200}{f816}今{f817}いま{f818}さら{f816}下{f817}した{f818}っ{f816}端{f817}ぱ{f818}の{f816}出番{f817}でばん{f818}でもないだろうよ{f801}{f816}殺{f817}ころ{f818}されたくなかったら{f816}道{f817}みち{f818}をあけな{f801}</target>
  </entry>
  <entry id="3">
    <source>{f812}阿修羅会の男{0000}{f87a}{8900}{f813}{0000}{0000}{24bf}{0200}{f816}調子{f817}ちょうし{f818}づくのもそこまでにしとけよ{f801}{f816}俺{f817}おれ{f818}の{f816}仲魔{f817}なかま{f818}を{f816}見{f817}み{f818}たらビビるぜぇえ{f801}</source>
    <target>{f812}阿修羅会の男{0000}{f87a}{8900}{f813}{0000}{0000}{24bf}{0200}{f816}調子{f817}ちょうし{f818}づくのもそこまでにしとけよ{f801}{f816}俺{f817}おれ{f818}の{f816}仲魔{f817}なかま{f818}を{f816}見{f817}み{f818}たらビビるぜぇえ{f801}</target>
  </entry>
  <entry id="4">
    <source>{f812}阿修羅会の男{0000}{f87a}{8900}{f813}{0000}{0000}{25bf}{0200}…ひ…{f816}必殺{f817}ひっさつ{f818}の{f816}霊的国防兵器{f817}れいてきこくぼうへいき{f818}でも{f801}かなわないだなんて…{f801}</source>
    <target>{f812}阿修羅会の男{0000}{f87a}{8900}{f813}{0000}{0000}{25bf}{0200}…ひ…{f816}必殺{f817}ひっさつ{f818}の{f816}霊的国防兵器{f817}れいてきこくぼうへいき{f818}でも{f801}かなわないだなんて…{f801}</target>
  </entry>
  <entry id="5">
    <source>{f812}阿修羅会の男{0000}{f87a}{8900}{f813}{0000}{0000}{26bf}{0200}た…たた…{f801}タヤマさぁぁあん…ッ{f801}</source>
    <target>{f812}阿修羅会の男{0000}{f87a}{8900}{f813}{0000}{0000}{26bf}{0200}た…たた…{f801}タヤマさぁぁあん…ッ{f801}</target>
  </entry>
  <entry id="6">
    <source>{f816}阿修羅会{f817}あしゅらかい{f818}の{f816}男{f817}おとこ{f818}は{f816}走{f817}はし{f818}り{f816}去{f817}さ{f818}っていった…{f801}</source>
    <target>{f816}阿修羅会{f817}あしゅらかい{f818}の{f816}男{f817}おとこ{f818}は{f816}走{f817}はし{f818}り{f816}去{f817}さ{f818}っていった…{f801}</target>
  </entry>
  <entry id="7">
    <source>{f812}ワルター{0000}{f87a}{0400}{f87b}{0400}{0a00}{0100}{0100}{f813}{0000}{0000}{27bf}{0200}{f816}結局{f817}けっきょく{f818} {f816}逃{f817}に{f818}げるのか{f801}こいつらは {f816}昔{f817}むかし{f818}から{f816}進歩{f817}しんぽ{f818}がねぇな…{f801}</source>
    <target>{f812}ワルター{0000}{f87a}{0400}{f87b}{0400}{0a00}{0100}{0100}{f813}{0000}{0000}{27bf}{0200}{f816}結局{f817}けっきょく{f818} {f816}逃{f817}に{f818}げるのか{f801}こいつらは {f816}昔{f817}むかし{f818}から{f816}進歩{f817}しんぽ{f818}がねぇな…{f801}</target>
  </entry>
  <entry id="8">
    <source>{f816}龍蛇{f817}りゅうじゃ{f818}の{f816}双鱗{f817}そうりん{f818}が{f801}{f816}手{f817}て{f818}の{f816}中{f817}なか{f818}で{f816}輝{f817}かがや{f818}きだした{f801}</source>
    <target>{f816}龍蛇{f817}りゅうじゃ{f818}の{f816}双鱗{f817}そうりん{f818}が{f801}{f816}手{f817}て{f818}の{f816}中{f817}なか{f818}で{f816}輝{f817}かがや{f818}きだした{f801}</target>
  </entry>
  <entry id="9">
    <source>{f812}声{0000}{f87a}{0200}{f813}{0100}{0000}{a4e5}{0600}オレは{f816}龍神{f817}りゅうじん{f818}コウガサブロウ{f801}{f816}必殺{f817}ひっさつ{f818}の{f816}霊的国防兵器{f817}れいてきこくぼうへいき{f818}の{f816}一柱{f817}ひとはしら{f818}だ{f801}</source>
    <target>{f812}声{0000}{f87a}{0200}{f813}{0100}{0000}{a4e5}{0600}オレは{f816}龍神{f817}りゅうじん{f818}コウガサブロウ{f801}{f816}必殺{f817}ひっさつ{f818}の{f816}霊的国防兵器{f817}れいてきこくぼうへいき{f818}の{f816}一柱{f817}ひとはしら{f818}だ{f801}</target>
  </entry>
  <entry id="10">
    <source>{f812}コウガサブロウ{0000}{f87a}{0200}{f813}{0100}{0000}{a3e5}{0600}お{f816}前{f817}まえ{f818}が{f816}何者{f817}なにもの{f818}かなんて どうでもいい{f801}{f816}依{f817}よ{f818}り{f816}代{f817}しろ{f818}を{f816}持{f817}も{f818}ってるなら{f816}主{f817}あるじ{f818}になってもらう{f801}{f802}{f813}{0100}{0000}{aae5}{0600}{f816}今後{f817}こんご{f818}ともよろしく{f801}</source>
    <target>{f812}コウガサブロウ{0000}{f87a}{0200}{f813}{0100}{0000}{a3e5}{0600}お{f816}前{f817}まえ{f818}が{f816}何者{f817}なにもの{f818}かなんて どうでもいい{f801}{f816}依{f817}よ{f818}り{f816}代{f817}しろ{f818}を{f816}持{f817}も{f818}ってるなら{f816}主{f817}あるじ{f818}になってもらう{f801}{f802}{f813}{0100}{0000}{aae5}{0600}{f816}今後{f817}こんご{f818}ともよろしく{f801}</target>
  </entry>
  <entry id="11">
    <source>{f804}{0500}{f874}{8401}${f842}{8401}{f804}{0000}の{f801}{f816}合体{f817}がったい{f818}が{f816}可能{f817}かのう{f818}になった{f801}</source>
    <target>{f804}{0500}{f874}{8401}${f842}{8401}{f804}{0000}の{f801}{f816}合体{f817}がったい{f818}が{f816}可能{f817}かのう{f818}になった{f801}</target>
  </entry>
  <entry id="12">
    <source>{f816}愛想{f817}あいそう{f818}の{f816}悪{f817}わる{f818}い{f816}男{f817}おとこ{f818}が{f816}立{f817}た{f818}っている{f801}</source>
    <target>{f816}愛想{f817}あいそう{f818}の{f816}悪{f817}わる{f818}い{f816}男{f817}おとこ{f818}が{f816}立{f817}た{f818}っている{f801}</target>
  </entry>
  <entry id="13">
    <source>{f812}愛想の悪い男{0000}{f87a}{2e00}{f813}{0100}{0000}{0d27}{0600}お お{f816}前{f817}まえ{f818}らッ{f801}コウガサブロウは{f816}何{f817}なに{f818}やってんだぁ…ッ?{f801}</source>
    <target>{f812}愛想の悪い男{0000}{f87a}{2e00}{f813}{0100}{0000}{0d27}{0600}お お{f816}前{f817}まえ{f818}らッ{f801}コウガサブロウは{f816}何{f817}なに{f818}やってんだぁ…ッ?{f801}</target>
  </entry>
  <entry id="14">
    <source>{f812}ワルター{0000}{f87a}{0400}{f813}{0100}{0000}{4b1b}{0600}…{f816}逃{f817}に{f818}げてくれるんなら{f816}早{f817}はや{f818}くしてくれ{f801}{f816}引{f817}ひ{f818}き{f816}留{f817}と{f818}めなんてしないからよ{f801}</source>
    <target>{f812}ワルター{0000}{f87a}{0400}{f813}{0100}{0000}{4b1b}{0600}…{f816}逃{f817}に{f818}げてくれるんなら{f816}早{f817}はや{f818}くしてくれ{f801}{f816}引{f817}ひ{f818}き{f816}留{f817}と{f818}めなんてしないからよ{f801}</target>
  </entry>
  <entry id="15">
    <source>{f812}愛想の悪い男{0000}{f87a}{2e00}{f813}{0100}{0000}{4426}{0600}い {f816}言{f817}い{f818}われんでも そうさせてもらうぜ{f801}{f816}俺{f817}おれ{f818}の{f816}役割{f817}やくわり{f818}は お{f816}前{f817}まえ{f818}らと{f816}戦{f817}たたか{f818}うことじゃねぇ{f801}{f802}タヤマさんを{f816}無限発電炉{f817}むげんはつでんろ{f818}ヤマトまで{f816}送{f817}おく{f818}る…{f801}その{f816}後{f817}あと{f818}のことは{f816}聞{f817}き{f818}いてねぇしよ{f801}</source>
    <target>{f812}愛想の悪い男{0000}{f87a}{2e00}{f813}{0100}{0000}{4426}{0600}い {f816}言{f817}い{f818}われんでも そうさせてもらうぜ{f801}{f816}俺{f817}おれ{f818}の{f816}役割{f817}やくわり{f818}は お{f816}前{f817}まえ{f818}らと{f816}戦{f817}たたか{f818}うことじゃねぇ{f801}{f802}タヤマさんを{f816}無限発電炉{f817}むげんはつでんろ{f818}ヤマトまで{f816}送{f817}おく{f818}る…{f801}その{f816}後{f817}あと{f818}のことは{f816}聞{f817}き{f818}いてねぇしよ{f801}</target>
  </entry>
  <entry id="16">
    <source>{f812}愛想の悪い男{0000}{f87a}{2e00}お{f816}前{f817}まえ{f818}の{f816}始末{f817}しまつ{f818}は{f816}例{f817}れい{f818}の『{f816}兵器{f817}へいき{f818}』に{f816}任{f817}まか{f818}せるぜ{f801}…{f816}行{f817}い{f818}って {f816}殺{f817}や{f818}られてこいや{f801}</source>
    <target>{f812}愛想の悪い男{0000}{f87a}{2e00}お{f816}前{f817}まえ{f818}の{f816}始末{f817}しまつ{f818}は{f816}例{f817}れい{f818}の『{f816}兵器{f817}へいき{f818}』に{f816}任{f817}まか{f818}せるぜ{f801}…{f816}行{f817}い{f818}って {f816}殺{f817}や{f818}られてこいや{f801}</target>
  </entry>
  <entry id="17">
    <source>{f816}愛想{f817}あいそう{f818}の{f816}悪{f817}わる{f818}い{f816}男{f817}おとこ{f818}は{f801}{f816}小走{f817}こばし{f818}りで{f816}立{f817}た{f818}ち{f816}去{f817}さ{f818}った…{f801}</source>
    <target>{f816}愛想{f817}あいそう{f818}の{f816}悪{f817}わる{f818}い{f816}男{f817}おとこ{f818}は{f801}{f816}小走{f817}こばし{f818}りで{f816}立{f817}た{f818}ち{f816}去{f817}さ{f818}った…{f801}</target>
  </entry>
  <entry id="104">
    <source>{f816}悪魔{f817}あくま{f818}は{f816}岩山{f817}いわやま{f818}になってしまった…{f801}</source>
    <target>{f816}悪魔{f817}あくま{f818}は{f816}岩山{f817}いわやま{f818}になってしまった…{f801}</target>
  </entry>
  <entry id="108">
    <source>{f816}目{f817}め{f818}の{f816}前{f817}まえ{f818}の{f816}岩山{f817}いわやま{f818}から{f816}声{f817}こえ{f818}が{f816}聞{f817}き{f818}こえてくる…{f801}</source>
    <target>{f816}目{f817}め{f818}の{f816}前{f817}まえ{f818}の{f816}岩山{f817}いわやま{f818}から{f816}声{f817}こえ{f818}が{f816}聞{f817}き{f818}こえてくる…{f801}</target>
  </entry>
  <entry id="111">
    <source>かつてコウガサブロウであった{f816}岩山{f817}いわやま{f818}が{f801}{f816}目{f817}め{f818}の{f816}前{f817}まえ{f818}に{f816}鎮座{f817}ちんざ{f818}している…{f801}</source>
    <target>かつてコウガサブロウであった{f816}岩山{f817}いわやま{f818}が{f801}{f816}目{f817}め{f818}の{f816}前{f817}まえ{f818}に{f816}鎮座{f817}ちんざ{f818}している…{f801}</target>
  </entry>
  <entry id="211">
    <source>コウガサブロウは もういない…{f801}</source>
    <target>コウガサブロウは もういない…{f801}</target>
  </entry>
</mbm>