<mbm>
  <entry id="0">
    <source>{f812}清治{0000}{f87a}{5300}{f87b}{5300}{0400}{0100}{0100}{f813}{0000}{0000}{a2fd}{0200}…啊,看,就是他们。{f801}{f802}{f813}{0000}{0000}{a3fd}{0200}阿辉,他们是我呼唤来的救世主。{f801}{ffff}</source>
    <target>{f812}清治{0000}{f87a}{5300}{f87b}{5300}{0400}{0100}{0100}{f813}{0000}{0000}{a2fd}{0200}…啊,看,就是他们。{f801}{f802}{f813}{0000}{0000}{a3fd}{0200}阿辉,他们是我呼唤来的救世主。{f801}{ffff}</target>
  </entry>
  <entry id="1">
    <source>{f812}约纳坦{0000}{f87a}{0300}{f87b}{0300}{0a00}{0100}{0100}{f87b}{0400}{0a00}{0100}{0100}{f813}{0000}{0000}{a4fd}{0200}『救世主』?{f801}你说我们…?{f801}{ffff}</source>
    <target>{f812}约纳坦{0000}{f87a}{0300}{f87b}{0300}{0a00}{0100}{0100}{f87b}{0400}{0a00}{0100}{0100}{f813}{0000}{0000}{a4fd}{0200}『救世主』?{f801}你说我们…?{f801}{ffff}</target>
  </entry>
  <entry id="2">
    <source>{f812}辉{0000}{f87a}{5400}{f87b}{5400}{0100}{0100}{0100}{f813}{0000}{0000}{a5fd}{0200}是吗…他们真的来了呢。{f801}{ffff}</source>
    <target>{f812}辉{0000}{f87a}{5400}{f87b}{5400}{0100}{0100}{0100}{f813}{0000}{0000}{a5fd}{0200}是吗…他们真的来了呢。{f801}{ffff}</target>
  </entry>
  <entry id="3">
    <source>{f812}清治{0000}{f87a}{5300}{f87b}{5300}{0400}{0100}{0100}{f813}{0000}{0000}{a7fd}{0200}…我想想…25年了,嘻嘻!{f801}{f802}{f813}{0000}{0000}{a8fd}{0200}多亏了我一直一直在祈祷啊,{f801}这下魔王普鲁托要完蛋啦。{f801}{ffff}</source>
    <target>{f812}清治{0000}{f87a}{5300}{f87b}{5300}{0400}{0100}{0100}{f813}{0000}{0000}{a7fd}{0200}…我想想…25年了,嘻嘻!{f801}{f802}{f813}{0000}{0000}{a8fd}{0200}多亏了我一直一直在祈祷啊,{f801}这下魔王普鲁托要完蛋啦。{f801}{ffff}</target>
  </entry>
  <entry id="4">
    <source>{f812}辉{0000}{f87a}{5400}{f87b}{5400}{0400}{0100}{0100}{f813}{0000}{0000}{a9fd}{0200}曾经与清治先生并肩作战的那个人{f801}一定也在天国祝福着我们吧…{f801}{ffff}</source>
    <target>{f812}辉{0000}{f87a}{5400}{f87b}{5400}{0400}{0100}{0100}{f813}{0000}{0000}{a9fd}{0200}曾经与清治先生并肩作战的那个人{f801}一定也在天国祝福着我们吧…{f801}{ffff}</target>
  </entry>
  <entry id="5">
    <source>{f812}清治{0000}{f87a}{5300}{f87b}{5300}{0400}{0100}{0100}{f813}{0000}{0000}{aafd}{0200}…对了,我怎么忘了,{f801}要去向神明大人道谢啊。{f801}{f802}{f813}{0000}{0000}{abfd}{0200}阿辉呀,{f801}救世主大人们就拜托你招待了。{f801}{ffff}</source>
    <target>{f812}清治{0000}{f87a}{5300}{f87b}{5300}{0400}{0100}{0100}{f813}{0000}{0000}{aafd}{0200}…对了,我怎么忘了,{f801}要去向神明大人道谢啊。{f801}{f802}{f813}{0000}{0000}{abfd}{0200}阿辉呀,{f801}救世主大人们就拜托你招待了。{f801}{ffff}</target>
  </entry>
  <entry id="6">
    <source>清治离开了{f801}{ffff}</source>
    <target>清治离开了{f801}{ffff}</target>
  </entry>
  <entry id="7">
    <source>{f812}辉{0000}{f87a}{5400}{f87b}{5400}{0400}{0100}{0100}{f813}{0000}{0000}{acfd}{0200}…呵。{f801}{f802}{f813}{0000}{0000}{adfd}{0200}也难怪几位脸上都是{f801}『到底发生了什么』的表情呢…{f801}{f802}{f813}{0000}{0000}{aefd}{0200}请不必担心,{f801}我们不会是你们的敌人。{f801}{ffff}</source>
    <target>{f812}辉{0000}{f87a}{5400}{f87b}{5400}{0400}{0100}{0100}{f813}{0000}{0000}{acfd}{0200}…呵。{f801}{f802}{f813}{0000}{0000}{adfd}{0200}也难怪几位脸上都是{f801}『到底发生了什么』的表情呢…{f801}{f802}{f813}{0000}{0000}{aefd}{0200}请不必担心,{f801}我们不会是你们的敌人。{f801}{ffff}</target>
  </entry>
  <entry id="8">
    <source>{f812}约纳坦{0000}{f87a}{0300}{f87b}{0300}{0a00}{0100}{0100}{f813}{0000}{0000}{affd}{0200}…您是什么意思?{f801}{ffff}</source>
    <target>{f812}约纳坦{0000}{f87a}{0300}{f87b}{0300}{0a00}{0100}{0100}{f813}{0000}{0000}{affd}{0200}…您是什么意思?{f801}{ffff}</target>
  </entry>
  <entry id="9">
    <source>{f812}辉{0000}{f87a}{5400}{f87b}{5400}{0c00}{0100}{0100}{f813}{0000}{0000}{b0fd}{0200}…我之前做了一个梦,梦中是一片纯白。{f801}{f802}{f813}{0000}{0000}{b1fd}{0200}在梦里,有几个自称褪色者的人{f801}告诉了我你们会来的事。{f801}{f802}{f813}{0000}{0000}{b2fd}{0200}他们说,你们来自另一个世界的{f801}某个『东之御门国』。{f801}{ffff}</source>
    <target>{f812}辉{0000}{f87a}{5400}{f87b}{5400}{0c00}{0100}{0100}{f813}{0000}{0000}{b0fd}{0200}…我之前做了一个梦,梦中是一片纯白。{f801}{f802}{f813}{0000}{0000}{b1fd}{0200}在梦里,有几个自称褪色者的人{f801}告诉了我你们会来的事。{f801}{f802}{f813}{0000}{0000}{b2fd}{0200}他们说,你们来自另一个世界的{f801}某个『东之御门国』。{f801}{ffff}</target>
  </entry>
  <entry id="10">
    <source>{f812}约纳坦{0000}{f87a}{0300}{f87b}{0300}{0700}{0100}{0200}{f813}{0000}{0000}{b3fd}{0200}另一个世界…?!{f801}{f802}{f813}{0000}{0000}{b4fd}{0200}那么,这里是{f801}另一个世界的东京…{f801}{ffff}</source>
    <target>{f812}约纳坦{0000}{f87a}{0300}{f87b}{0300}{0700}{0100}{0200}{f813}{0000}{0000}{b3fd}{0200}另一个世界…?!{f801}{f802}{f813}{0000}{0000}{b4fd}{0200}那么,这里是{f801}另一个世界的东京…{f801}{ffff}</target>
  </entry>
  <entry id="11">
    <source>{f812}辉{0000}{f87a}{5400}{f87b}{5400}{0400}{0100}{0100}{f813}{0000}{0000}{b5fd}{0200}一开始,我以为这只是一个单纯的梦。{f801}{f802}{f87b}{5400}{0100}{0100}{0100}{f813}{0000}{0000}{b6fd}{0200}但当我醒来时,{f801}我发现手里握着这个东西。{f801}{ffff}</source>
    <target>{f812}辉{0000}{f87a}{5400}{f87b}{5400}{0400}{0100}{0100}{f813}{0000}{0000}{b5fd}{0200}一开始,我以为这只是一个单纯的梦。{f801}{f802}{f87b}{5400}{0100}{0100}{0100}{f813}{0000}{0000}{b6fd}{0200}但当我醒来时,{f801}我发现手里握着这个东西。{f801}{ffff}</target>
  </entry>
  <entry id="12">
    <source>辉向{f843}{0000}一行人{f801}展示了一个小遥控器{f801}{ffff}</source>
    <target>辉向{f843}{0000}一行人{f801}展示了一个小遥控器{f801}{ffff}</target>
  </entry>
  <entry id="13">
    <source>{f812}沃尔特{0000}{f87a}{0400}{f87b}{0400}{0700}{0100}{0200}{f87b}{0300}{0700}{0100}{0200}{f813}{0000}{0000}{b7fd}{0200}那是大和无限发电炉的{f801}…什么什么器!{f801}{ffff}</source>
    <target>{f812}沃尔特{0000}{f87a}{0400}{f87b}{0400}{0700}{0100}{0200}{f87b}{0300}{0700}{0100}{0200}{f813}{0000}{0000}{b7fd}{0200}那是大和无限发电炉的{f801}…什么什么器!{f801}{ffff}</target>
  </entry>
  <entry id="14">
    <source>{f812}辉{0000}{f87a}{5400}{f87b}{5400}{0400}{0100}{0100}{f813}{0000}{0000}{b8fd}{0200}褪色者说,{f801}你们会想要这个东西。{f801}{ffff}</source>
    <target>{f812}辉{0000}{f87a}{5400}{f87b}{5400}{0400}{0100}{0100}{f813}{0000}{0000}{b8fd}{0200}褪色者说,{f801}你们会想要这个东西。{f801}{ffff}</target>
  </entry>
  <entry id="15">
    <source>{f812}辉{0000}{f87a}{5400}{f87b}{5400}{0c00}{0100}{0100}{f813}{0000}{0000}{bafd}{0200}褪色者有什么用意{f801}我对此一无所知…{f801}{ffff}</source>
    <target>{f812}辉{0000}{f87a}{5400}{f87b}{5400}{0c00}{0100}{0100}{f813}{0000}{0000}{bafd}{0200}褪色者有什么用意{f801}我对此一无所知…{f801}{ffff}</target>
  </entry>
  <entry id="16">
    <source>{f812}辉{0000}{f87a}{5400}{f87b}{5400}{0c00}{0100}{0100}{f813}{0000}{0000}{bbfd}{0200}反正我们在普鲁托的毒气里{f801}也已经撑不了太久了…{f801}{ffff}</source>
    <target>{f812}辉{0000}{f87a}{5400}{f87b}{5400}{0c00}{0100}{0100}{f813}{0000}{0000}{bbfd}{0200}反正我们在普鲁托的毒气里{f801}也已经撑不了太久了…{f801}{ffff}</target>
  </entry>
  <entry id="17">
    <source>{f812}辉{0000}{f87a}{5400}{f87b}{5400}{0400}{0100}{0100}{f813}{0000}{0000}{bcfd}{0200}…但是,如今真的见到了你们,{f801}我却变得想赌一把这个可能性。{f801}{f802}{f813}{0000}{0000}{bdfd}{0200}如果你们真的是清治先生所说的救世主,{f801}我希望你们能去打倒魔王普鲁托。{f801}{ffff}</source>
    <target>{f812}辉{0000}{f87a}{5400}{f87b}{5400}{0400}{0100}{0100}{f813}{0000}{0000}{bcfd}{0200}…但是,如今真的见到了你们,{f801}我却变得想赌一把这个可能性。{f801}{f802}{f813}{0000}{0000}{bdfd}{0200}如果你们真的是清治先生所说的救世主,{f801}我希望你们能去打倒魔王普鲁托。{f801}{ffff}</target>
  </entry>
  <entry id="18">
    <source>{f812}辉{0000}{f87a}{5400}{f87b}{5400}{0c00}{0100}{0100}{f813}{0000}{0000}{befd}{0200}…这个遥控器就是报酬。{f801}你们觉得怎么样…?{f801}{ffff}</source>
    <target>{f812}辉{0000}{f87a}{5400}{f87b}{5400}{0c00}{0100}{0100}{f813}{0000}{0000}{befd}{0200}…这个遥控器就是报酬。{f801}你们觉得怎么样…?{f801}{ffff}</target>
  </entry>
  <entry id="19">
    <source>接受{f801}拒绝{f801}{ffff}</source>
    <target>接受{f801}拒绝{f801}{ffff}</target>
  </entry>
  <entry id="20">
    <source>{f812}辉{0000}{f87a}{5400}{f87b}{5400}{0400}{0100}{0100}{f813}{0000}{0000}{bffd}{0200}…我真的很高兴。{f801}{ffff}</source>
    <target>{f812}辉{0000}{f87a}{5400}{f87b}{5400}{0400}{0100}{0100}{f813}{0000}{0000}{bffd}{0200}…我真的很高兴。{f801}{ffff}</target>
  </entry>
  <entry id="21">
    <source>{f812}辉{0000}{f87a}{5400}{f87b}{5400}{0100}{0100}{0100}{f813}{0000}{0000}{c0fd}{0200}普鲁托城位于此地的东南方向,{f801}魔王普鲁托就在那里。{f801}{f802}{f813}{0000}{0000}{c1fd}{0200}一路上你们少不了要遇到普鲁托的爪牙,{f801}我把它们的数据传给你们吧。{f801}{ffff}</source>
    <target>{f812}辉{0000}{f87a}{5400}{f87b}{5400}{0100}{0100}{0100}{f813}{0000}{0000}{c0fd}{0200}普鲁托城位于此地的东南方向,{f801}魔王普鲁托就在那里。{f801}{f802}{f813}{0000}{0000}{c1fd}{0200}一路上你们少不了要遇到普鲁托的爪牙,{f801}我把它们的数据传给你们吧。{f801}{ffff}</target>
  </entry>
  <entry id="22">
    <source>辉从怀里取出一个仪式护手,{f801}把数据传了过来{f801}{ffff}</source>
    <target>辉从怀里取出一个仪式护手,{f801}把数据传了过来{f801}{ffff}</target>
  </entry>
  <entry id="23">
    <source>{f812}辉{0000}{f87a}{5400}{f87b}{5400}{0100}{0100}{0100}{f813}{0000}{0000}{c4fd}{0200}这是以前我们一位勇闯普鲁托城的挚友留{f801}下的遗物。他会很高兴它能派上用场吧…{f801}{ffff}</source>
    <target>{f812}辉{0000}{f87a}{5400}{f87b}{5400}{0100}{0100}{0100}{f813}{0000}{0000}{c4fd}{0200}这是以前我们一位勇闯普鲁托城的挚友留{f801}下的遗物。他会很高兴它能派上用场吧…{f801}{ffff}</target>
  </entry>
  <entry id="24">
    <source>{f812}辉{0000}{f87a}{5400}{f87b}{5400}{0c00}{0100}{0100}{f813}{0000}{0000}{c5fd}{0200}我们相信着神,却没有被神选中。{f801}请为这样的我们带来希望之光吧…{f801}{f802}{f813}{0000}{0000}{c6fd}{0200}打倒普鲁托的事,就拜托你们了。{f801}{ffff}</source>
    <target>{f812}辉{0000}{f87a}{5400}{f87b}{5400}{0c00}{0100}{0100}{f813}{0000}{0000}{c5fd}{0200}我们相信着神,却没有被神选中。{f801}请为这样的我们带来希望之光吧…{f801}{f802}{f813}{0000}{0000}{c6fd}{0200}打倒普鲁托的事,就拜托你们了。{f801}{ffff}</target>
  </entry>
  <entry id="25">
    <source>{f812}辉{0000}{f87a}{5400}{f87b}{5400}{0100}{0100}{0100}{f813}{0000}{0000}{c8fd}{0200}这样吗…{f801}{f802}{f813}{0000}{0000}{c9fd}{0200}我会一直在这里,{f801}如果改变主意了,就来找我吧。{f801}{ffff}</source>
    <target>{f812}辉{0000}{f87a}{5400}{f87b}{5400}{0100}{0100}{0100}{f813}{0000}{0000}{c8fd}{0200}这样吗…{f801}{f802}{f813}{0000}{0000}{c9fd}{0200}我会一直在这里,{f801}如果改变主意了,就来找我吧。{f801}{ffff}</target>
  </entry>
  <entry id="100">
    <source>{f812}约纳坦{0000}{f87a}{0300}{f87b}{0300}{0800}{0100}{0100}{f87b}{0400}{0a00}{0100}{0100}{f813}{0000}{0000}{a1fd}{0200}呃…!这垃圾都堆成山了…{f801}{ffff}</source>
    <target>{f812}约纳坦{0000}{f87a}{0300}{f87b}{0300}{0800}{0100}{0100}{f87b}{0400}{0a00}{0100}{0100}{f813}{0000}{0000}{a1fd}{0200}呃…!这垃圾都堆成山了…{f801}{ffff}</target>
  </entry>
  <entry id="102">
    <source>{f812}辉{0000}{f87a}{5400}{f87b}{5400}{0400}{0100}{0100}{f813}{0000}{0000}{a6fd}{0200}你真的很努力啊,清治先生。{f801}{ffff}</source>
    <target>{f812}辉{0000}{f87a}{5400}{f87b}{5400}{0400}{0100}{0100}{f813}{0000}{0000}{a6fd}{0200}你真的很努力啊,清治先生。{f801}{ffff}</target>
  </entry>
  <entry id="114">
    <source>{f812}约纳坦{0000}{f87a}{0300}{f87b}{0300}{0200}{0100}{0100}{f87b}{0400}{0300}{0100}{0100}{f813}{0000}{0000}{b9fd}{0200}也就是说,我们还要再一次{f801}开启魔界之门吗…?{f801}{ffff}</source>
    <target>{f812}约纳坦{0000}{f87a}{0300}{f87b}{0300}{0200}{0100}{0100}{f87b}{0400}{0300}{0100}{0100}{f813}{0000}{0000}{b9fd}{0200}也就是说,我们还要再一次{f801}开启魔界之门吗…?{f801}{ffff}</target>
  </entry>
  <entry id="122">
    <source>{f812}巴洛斯{0000}{f87a}{0200}{f813}{0000}{0000}{c2fd}{0200}{f843}{0000}大人,{f801}我接收到了这个东京的地图数据。{f801}{f802}{f813}{0000}{0000}{c3fd}{0200}地图导航等功能{f801}现在可以使用了。{f801}{ffff}</source>
    <target>{f812}巴洛斯{0000}{f87a}{0200}{f813}{0000}{0000}{c2fd}{0200}{f843}{0000}大人,{f801}我接收到了这个东京的地图数据。{f801}{f802}{f813}{0000}{0000}{c3fd}{0200}地图导航等功能{f801}现在可以使用了。{f801}{ffff}</target>
  </entry>
  <entry id="124">
    <source>{f812}巴洛斯{0000}{f87a}{0200}{f813}{0100}{0000}{b21a}{0600}我把新任务{f801}添加进列表里了哦。{f801}{ffff}</source>
    <target>{f812}巴洛斯{0000}{f87a}{0200}{f813}{0100}{0000}{b21a}{0600}我把新任务{f801}添加进列表里了哦。{f801}{ffff}</target>
  </entry>
  <entry id="126">
    <source>{f812}辉{0000}{f87a}{5400}{f87b}{5400}{0400}{0100}{0100}{f813}{0000}{0000}{cafd}{0200}…你们回来了呢。{f801}{f802}{f813}{0000}{0000}{cbfd}{0200}如果你们真的是清治先生所说的救世主,{f801}我希望你们能去打倒魔王普鲁托。{f801}{ffff}</source>
    <target>{f812}辉{0000}{f87a}{5400}{f87b}{5400}{0400}{0100}{0100}{f813}{0000}{0000}{cafd}{0200}…你们回来了呢。{f801}{f802}{f813}{0000}{0000}{cbfd}{0200}如果你们真的是清治先生所说的救世主,{f801}我希望你们能去打倒魔王普鲁托。{f801}{ffff}</target>
  </entry>
  <entry id="127">
    <source>{f812}辉{0000}{f87a}{5400}{f87b}{5400}{0c00}{0100}{0100}{f813}{0000}{0000}{ccfd}{0200}…这个遥控器就是报酬。{f801}你们觉得怎么样…?{f801}{ffff}</source>
    <target>{f812}辉{0000}{f87a}{5400}{f87b}{5400}{0c00}{0100}{0100}{f813}{0000}{0000}{ccfd}{0200}…这个遥控器就是报酬。{f801}你们觉得怎么样…?{f801}{ffff}</target>
  </entry>
</mbm>