<mbm>
  <entry id="0">
    <source>仪式护手突然开始发光{f801}{f802}仪式护手的液晶屏幕上{f801}出现了什么东西…{f801}{ffff}</source>
    <target>仪式护手突然开始发光{f801}{f802}仪式护手的液晶屏幕上{f801}出现了什么东西…{f801}{ffff}</target>
  </entry>
  <entry id="1">
    <source>{f812}护手上的影像{0000}{f87a}{0200}……{f801}{f802}{f813}{0000}{0000}{1227}{0000}你好,人类。{f801}{f802}{f813}{0000}{0000}{1327}{0000}我叫巴洛斯,{f801}是人工智能导航。{f801}{ffff}</source>
    <target>{f812}护手上的影像{0000}{f87a}{0200}……{f801}{f802}{f813}{0000}{0000}{1227}{0000}你好,人类。{f801}{f802}{f813}{0000}{0000}{1327}{0000}我叫巴洛斯,{f801}是人工智能导航。{f801}{ffff}</target>
  </entry>
  <entry id="2">
    <source>{f812}巴洛斯{0000}{f87a}{0200}{f813}{0000}{0000}{1427}{0000}我已认证{f801}你为我的主人。{f801}{ffff}</source>
    <target>{f812}巴洛斯{0000}{f87a}{0200}{f813}{0000}{0000}{1427}{0000}我已认证{f801}你为我的主人。{f801}{ffff}</target>
  </entry>
  <entry id="3">
    <source>{f812}霍普{0000}{f87a}{0800}{f813}{0000}{0000}{1627}{0000}我是霍普。{f801}{f802}{f813}{0000}{0000}{1727}{0000}我正通过巴洛斯{f801}确认你们的位置。{f801}{f802}{f813}{0000}{0000}{1827}{0000}…看来你们都已经进入奈落了,{f801}那我就来讲解一下你们首项训练的事宜。{f801}{ffff}</source>
    <target>{f812}霍普{0000}{f87a}{0800}{f813}{0000}{0000}{1627}{0000}我是霍普。{f801}{f802}{f813}{0000}{0000}{1727}{0000}我正通过巴洛斯{f801}确认你们的位置。{f801}{f802}{f813}{0000}{0000}{1827}{0000}…看来你们都已经进入奈落了,{f801}那我就来讲解一下你们首项训练的事宜。{f801}{ffff}</target>
  </entry>
  <entry id="4">
    <source>{f812}霍普{0000}{f87a}{0800}{f813}{0000}{0000}{1927}{0000}你们首先需要与恶魔作战,{f801}以此来学会战斗的基本技巧。{f801}{f802}{f813}{0000}{0000}{1a27}{0000}身为武士,{f801}与恶魔战斗就是其本职。{f801}{f802}{f813}{0000}{0000}{1b27}{0000}你们的任务是消灭一只奈落里{f801}出现的恶魔,任何恶魔都可以。{f801}{ffff}</source>
    <target>{f812}霍普{0000}{f87a}{0800}{f813}{0000}{0000}{1927}{0000}你们首先需要与恶魔作战,{f801}以此来学会战斗的基本技巧。{f801}{f802}{f813}{0000}{0000}{1a27}{0000}身为武士,{f801}与恶魔战斗就是其本职。{f801}{f802}{f813}{0000}{0000}{1b27}{0000}你们的任务是消灭一只奈落里{f801}出现的恶魔,任何恶魔都可以。{f801}{ffff}</target>
  </entry>
  <entry id="5">
    <source>{f812}霍普{0000}{f87a}{0800}{f813}{0000}{0000}{1c27}{0000}住在你们护手里的妖精巴洛斯{f801}会为你们提供支援。{f801}{f802}{f813}{0000}{0000}{1d27}{0000}完毕。{f801}所有人立即开始实地训练。{f801}{ffff}</source>
    <target>{f812}霍普{0000}{f87a}{0800}{f813}{0000}{0000}{1c27}{0000}住在你们护手里的妖精巴洛斯{f801}会为你们提供支援。{f801}{f802}{f813}{0000}{0000}{1d27}{0000}完毕。{f801}所有人立即开始实地训练。{f801}{ffff}</target>
  </entry>
  <entry id="6">
    <source>{f812}巴洛斯{0000}{f87a}{0200}{f813}{0000}{0000}{1e27}{0000}我可以介绍一下菜单的使用方法。{f801}需要吗?{f801}{ffff}</source>
    <target>{f812}巴洛斯{0000}{f87a}{0200}{f813}{0000}{0000}{1e27}{0000}我可以介绍一下菜单的使用方法。{f801}需要吗?{f801}{ffff}</target>
  </entry>
  <entry id="7">
    <source>需要{f801}不必了{f801}{ffff}</source>
    <target>需要{f801}不必了{f801}{ffff}</target>
  </entry>
  <entry id="8">
    <source>{f812}巴洛斯{0000}{f87a}{0200}{f813}{0000}{0000}{1f27}{0000}OK,{f801}那我们就跳过了。{f801}{ffff}</source>
    <target>{f812}巴洛斯{0000}{f87a}{0200}{f813}{0000}{0000}{1f27}{0000}OK,{f801}那我们就跳过了。{f801}{ffff}</target>
  </entry>
  <entry id="9">
    <source>现在可以在下屏打开{f804}{0500}菜单{f804}{0000}了{f801}你可以在菜单里进行确认状态、{f801}使用道具等重要操作{f801}{f802}在探索中,你可以通过{f801}按Y键打开菜单{f801}{f802}随着流程推进,菜单将会解锁更多功能{f801}{ffff}</source>
    <target>现在可以在下屏打开{f804}{0500}菜单{f804}{0000}了{f801}你可以在菜单里进行确认状态、{f801}使用道具等重要操作{f801}{f802}在探索中,你可以通过{f801}按Y键打开菜单{f801}{f802}随着流程推进,菜单将会解锁更多功能{f801}{ffff}</target>
  </entry>
  <entry id="10">
    <source>{f812}巴洛斯{0000}{f87a}{0200}{f813}{0000}{0000}{2027}{0000}OK了吗?{f801}{ffff}</source>
    <target>{f812}巴洛斯{0000}{f87a}{0200}{f813}{0000}{0000}{2027}{0000}OK了吗?{f801}{ffff}</target>
  </entry>
  <entry id="11">
    <source>OK了{f801}再确认一次{f801}{ffff}</source>
    <target>OK了{f801}再确认一次{f801}{ffff}</target>
  </entry>
  <entry id="12">
    <source>{f812}巴洛斯{0000}{f87a}{0200}{f813}{0000}{0000}{2127}{0000}没问题。{f801}我重新显示一遍。{f801}{ffff}</source>
    <target>{f812}巴洛斯{0000}{f87a}{0200}{f813}{0000}{0000}{2127}{0000}没问题。{f801}我重新显示一遍。{f801}{ffff}</target>
  </entry>
  <entry id="13">
    <source>{f812}巴洛斯{0000}{f87a}{0200}{f813}{0000}{0000}{2227}{0000}以防万一,{f801}要记得存档哦。{f801}{ffff}</source>
    <target>{f812}巴洛斯{0000}{f87a}{0200}{f813}{0000}{0000}{2227}{0000}以防万一,{f801}要记得存档哦。{f801}{ffff}</target>
  </entry>
  <entry id="14">
    <source>你可以在菜单界面{f801}进行存档与读取{f801}{f802}要进行存档与读取,{f801}在主菜单界面选择『{f804}{0500}巴洛斯{f804}{0000}』,{f801}然后选择『{f804}{0500}存档{f804}{0000}』或『{f804}{0500}读取{f804}{0000}』即可{f801}{ffff}</source>
    <target>你可以在菜单界面{f801}进行存档与读取{f801}{f802}要进行存档与读取,{f801}在主菜单界面选择『{f804}{0500}巴洛斯{f804}{0000}』,{f801}然后选择『{f804}{0500}存档{f804}{0000}』或『{f804}{0500}读取{f804}{0000}』即可{f801}{ffff}</target>
  </entry>
  <entry id="15">
    <source>{f812}巴洛斯{0000}{f87a}{0200}{f813}{0000}{0000}{2327}{0000}OK了吗?{f801}{ffff}</source>
    <target>{f812}巴洛斯{0000}{f87a}{0200}{f813}{0000}{0000}{2327}{0000}OK了吗?{f801}{ffff}</target>
  </entry>
  <entry id="16">
    <source>OK了{f801}再确认一次{f801}{ffff}</source>
    <target>OK了{f801}再确认一次{f801}{ffff}</target>
  </entry>
  <entry id="17">
    <source>{f812}巴洛斯{0000}{f87a}{0200}{f813}{0000}{0000}{2427}{0000}没问题。{f801}我重新显示一遍。{f801}{ffff}</source>
    <target>{f812}巴洛斯{0000}{f87a}{0200}{f813}{0000}{0000}{2427}{0000}没问题。{f801}我重新显示一遍。{f801}{ffff}</target>
  </entry>
  <entry id="18">
    <source>{f812}巴洛斯{0000}{f87a}{0200}{f813}{0000}{0000}{2627}{0000}这就是我目前能提供的全部协助。{f801}{ffff}</source>
    <target>{f812}巴洛斯{0000}{f87a}{0200}{f813}{0000}{0000}{2627}{0000}这就是我目前能提供的全部协助。{f801}{ffff}</target>
  </entry>
  <entry id="19">
    <source>{f812}巴洛斯{0000}{f87a}{0200}{f813}{0000}{0000}{2527}{0000}下回见,{f801}{f843}{0000}大人。{f801}{ffff}</source>
    <target>{f812}巴洛斯{0000}{f87a}{0200}{f813}{0000}{0000}{2527}{0000}下回见,{f801}{f843}{0000}大人。{f801}{ffff}</target>
  </entry>
  <entry id="20">
    <source>这里的气氛是你此前从未感受过的…{f801}{f802}你感到一股寒意沿着脊柱慢慢渗下…{f801}{ffff}</source>
    <target>这里的气氛是你此前从未感受过的…{f801}{f802}你感到一股寒意沿着脊柱慢慢渗下…{f801}{ffff}</target>
  </entry>
  <entry id="102">
    <source>{f812}巴洛斯{0000}{f87a}{0200}{f813}{0000}{0000}{1527}{0000}很高兴见到你。{f801}{ffff}</source>
    <target>{f812}巴洛斯{0000}{f87a}{0200}{f813}{0000}{0000}{1527}{0000}很高兴见到你。{f801}{ffff}</target>
  </entry>
</mbm>