<mbm>
  <entry id="0">
    <source>{f812}店主{0000}{f87a}{1800}{f813}{0000}{0000}{9922}{0400}…おぉ いいとこに{f816}来{f817}き{f818}たな{f801}{f816}今{f817}いま{f818}しがた{f816}掲示板{f817}けいじばん{f818}を{f816}更新{f817}こうしん{f818}したところなんだ{f801}{f802}{f813}{0000}{0000}{9a22}{0400}{f843}{0000}が{f801}{f816}文句{f817}もんく{f818}なしに{f816}総合{f817}そうごう{f818}{f816}部門{f817}ぶもん{f818}の1{f816}位{f817}い{f818}だ{f801}{ffff}</source>
    <target>{f812}店主{0000}{f87a}{1800}{f813}{0000}{0000}{9922}{0400}…おぉ いいとこに{f816}来{f817}き{f818}たな{f801}{f816}今{f817}いま{f818}しがた{f816}掲示板{f817}けいじばん{f818}を{f816}更新{f817}こうしん{f818}したところなんだ{f801}{f802}{f813}{0000}{0000}{9a22}{0400}{f843}{0000}が{f801}{f816}文句{f817}もんく{f818}なしに{f816}総合{f817}そうごう{f818}{f816}部門{f817}ぶもん{f818}の1{f816}位{f817}い{f818}だ{f801}{ffff}</target>
  </entry>
  <entry id="1">
    <source>{f812}イザボー{0000}{f87a}{0500}{f87b}{0500}{0100}{0100}{0100}{f813}{0000}{0000}{9b22}{0400}…と{f816}言{f817}い{f818}うことは?{f801}{ffff}</source>
    <target>{f812}イザボー{0000}{f87a}{0500}{f87b}{0500}{0100}{0100}{0100}{f813}{0000}{0000}{9b22}{0400}…と{f816}言{f817}い{f818}うことは?{f801}{ffff}</target>
  </entry>
  <entry id="2">
    <source>{f812}店主{0000}{f87a}{1800}{f813}{0000}{0000}{9c22}{0400}{f843}{0000}はな{f801}{f816}初代{f817}しょだい{f818}のチャンピオンになったんだよ{f801}{ffff}</source>
    <target>{f812}店主{0000}{f87a}{1800}{f813}{0000}{0000}{9c22}{0400}{f843}{0000}はな{f801}{f816}初代{f817}しょだい{f818}のチャンピオンになったんだよ{f801}{ffff}</target>
  </entry>
  <entry id="3">
    <source>{f812}店主{0000}{f87a}{1800}{f813}{0000}{0000}{a022}{0400}いずれチャンピオンの{f816}噂{f817}うわさ{f818}が{f801}{f816}東京中{f817}とうきょうじゅう{f818}に{f816}知{f817}し{f818}れ{f816}渡{f817}わた{f818}るだろうさ{f801}{f802}{f813}{0000}{0000}{a122}{0400}どっか{f816}街{f817}まち{f818}に{f816}行{f817}い{f818}くなら{f816}気{f817}き{f818}をつけなよ?{f801}きっと{f816}人{f817}ひと{f818}が{f816}寄{f817}よ{f818}ってきて{f816}揉{f817}も{f818}みくちゃだぜ{f801}{ffff}</source>
    <target>{f812}店主{0000}{f87a}{1800}{f813}{0000}{0000}{a022}{0400}いずれチャンピオンの{f816}噂{f817}うわさ{f818}が{f801}{f816}東京中{f817}とうきょうじゅう{f818}に{f816}知{f817}し{f818}れ{f816}渡{f817}わた{f818}るだろうさ{f801}{f802}{f813}{0000}{0000}{a122}{0400}どっか{f816}街{f817}まち{f818}に{f816}行{f817}い{f818}くなら{f816}気{f817}き{f818}をつけなよ?{f801}きっと{f816}人{f817}ひと{f818}が{f816}寄{f817}よ{f818}ってきて{f816}揉{f817}も{f818}みくちゃだぜ{f801}{ffff}</target>
  </entry>
  <entry id="4">
    <source>{f812}唇の青い男{0000}{f87a}{3c00}{f813}{0000}{0000}{a222}{0400}…ん?{f801}{f802}{f813}{0000}{0000}{a322}{0400}あんた たしか…{f801}{ffff}</source>
    <target>{f812}唇の青い男{0000}{f87a}{3c00}{f813}{0000}{0000}{a222}{0400}…ん?{f801}{f802}{f813}{0000}{0000}{a322}{0400}あんた たしか…{f801}{ffff}</target>
  </entry>
  <entry id="5">
    <source>{f816}唇{f817}くちびる{f818}の{f816}青{f817}あお{f818}い{f816}男{f817}おとこ{f818}が{f843}{0000}を{f801}{f816}舐{f817}な{f818}めるように{f816}見{f817}み{f818}ている…{f801}{ffff}</source>
    <target>{f816}唇{f817}くちびる{f818}の{f816}青{f817}あお{f818}い{f816}男{f817}おとこ{f818}が{f843}{0000}を{f801}{f816}舐{f817}な{f818}めるように{f816}見{f817}み{f818}ている…{f801}{ffff}</target>
  </entry>
  <entry id="6">
    <source>{f812}唇の青い男{0000}{f87a}{3c00}{f813}{0000}{0000}{a422}{0400}やっぱり そうだッ!{f801}あんたが{f843}{0000}だろう?{f801}{f802}{f813}{0000}{0000}{a522}{0400}{f816}俺{f817}おれ{f818}の{f816}知{f817}し{f818}り{f816}合{f817}あ{f818}いが{f816}商会{f817}しょうかい{f818}であんたを{f816}見{f817}み{f818}たってよ{f801}それで{f816}聞{f817}き{f818}いてたからさ{f801}{ffff}</source>
    <target>{f812}唇の青い男{0000}{f87a}{3c00}{f813}{0000}{0000}{a422}{0400}やっぱり そうだッ!{f801}あんたが{f843}{0000}だろう?{f801}{f802}{f813}{0000}{0000}{a522}{0400}{f816}俺{f817}おれ{f818}の{f816}知{f817}し{f818}り{f816}合{f817}あ{f818}いが{f816}商会{f817}しょうかい{f818}であんたを{f816}見{f817}み{f818}たってよ{f801}それで{f816}聞{f817}き{f818}いてたからさ{f801}{ffff}</target>
  </entry>
  <entry id="7">
    <source>{f812}唇の青い男{0000}{f87a}{3c00}{f813}{0000}{0000}{a622}{0400}…へぇ {f816}想像{f817}そうぞう{f818}してたより{f816}若{f817}わか{f818}いじゃないの{f801}{ffff}</source>
    <target>{f812}唇の青い男{0000}{f87a}{3c00}{f813}{0000}{0000}{a622}{0400}…へぇ {f816}想像{f817}そうぞう{f818}してたより{f816}若{f817}わか{f818}いじゃないの{f801}{ffff}</target>
  </entry>
  <entry id="8">
    <source>{f812}女の声{0000}{f813}{0000}{0000}{a722}{0400}なに? {f843}{0000}?{f801}どこよ どこ?{f801}{ffff}</source>
    <target>{f812}女の声{0000}{f813}{0000}{0000}{a722}{0400}なに? {f843}{0000}?{f801}どこよ どこ?{f801}{ffff}</target>
  </entry>
  <entry id="9">
    <source>{f812}男の声{0000}{f813}{0000}{0000}{a822}{0400}{f843}{0000}が{f801}{f816}上野{f817}うえの{f818}に{f816}来{f817}き{f818}てるってのか…?{f801}{ffff}</source>
    <target>{f812}男の声{0000}{f813}{0000}{0000}{a822}{0400}{f843}{0000}が{f801}{f816}上野{f817}うえの{f818}に{f816}来{f817}き{f818}てるってのか…?{f801}{ffff}</target>
  </entry>
  <entry id="10">
    <source>{f843}{0000}の{f816}噂{f817}うわさ{f818}を{f816}聞{f817}き{f818}きつけ{f801}{f816}地下街{f817}ちかがい{f818}の{f816}人々{f817}ひとびと{f818}が{f816}集{f817}あつ{f818}まってきた{f801}{ffff}</source>
    <target>{f843}{0000}の{f816}噂{f817}うわさ{f818}を{f816}聞{f817}き{f818}きつけ{f801}{f816}地下街{f817}ちかがい{f818}の{f816}人々{f817}ひとびと{f818}が{f816}集{f817}あつ{f818}まってきた{f801}{ffff}</target>
  </entry>
  <entry id="11">
    <source>{f812}イザボー{0000}{f87a}{0500}{f87b}{0500}{0600}{0100}{0100}{f813}{0000}{0000}{a922}{0400}{f843}{0000}の{f816}人気{f817}にんき{f818}も{f801}たいしたものね{f801}{ffff}</source>
    <target>{f812}イザボー{0000}{f87a}{0500}{f87b}{0500}{0600}{0100}{0100}{f813}{0000}{0000}{a922}{0400}{f843}{0000}の{f816}人気{f817}にんき{f818}も{f801}たいしたものね{f801}{ffff}</target>
  </entry>
  <entry id="12">
    <source>{f812}男の声{0000}{f813}{0000}{0000}{aa22}{0400}ぃよッ この{f816}男前{f817}おとこまえ{f818}ぇ{f801}あんたがいりゃ{f816}東京{f817}とうきょう{f818}も{f816}安泰{f817}あんたい{f818}だ{f801}{ffff}</source>
    <target>{f812}男の声{0000}{f813}{0000}{0000}{aa22}{0400}ぃよッ この{f816}男前{f817}おとこまえ{f818}ぇ{f801}あんたがいりゃ{f816}東京{f817}とうきょう{f818}も{f816}安泰{f817}あんたい{f818}だ{f801}{ffff}</target>
  </entry>
  <entry id="13">
    <source>{f812}女の声{0000}{f813}{0000}{0000}{ab22}{0400}あぁ{f816}見{f817}み{f818}ているだけで{f816}勇気{f817}ゆうき{f818}が{f816}湧{f817}わ{f818}くわ{f801}{f802}{f813}{0000}{0000}{ac22}{0400}あなたの{f816}活躍{f817}かつやく{f818}が{f801}{f816}私{f817}わたし{f818}たちの{f816}生{f817}い{f818}きる{f816}希望{f817}きぼう{f818}よ{f801}{ffff}</source>
    <target>{f812}女の声{0000}{f813}{0000}{0000}{ab22}{0400}あぁ{f816}見{f817}み{f818}ているだけで{f816}勇気{f817}ゆうき{f818}が{f816}湧{f817}わ{f818}くわ{f801}{f802}{f813}{0000}{0000}{ac22}{0400}あなたの{f816}活躍{f817}かつやく{f818}が{f801}{f816}私{f817}わたし{f818}たちの{f816}生{f817}い{f818}きる{f816}希望{f817}きぼう{f818}よ{f801}{ffff}</target>
  </entry>
  <entry id="14">
    <source>エラーです{f801}{ffff}</source>
    <target>エラーです{f801}{ffff}</target>
  </entry>
  <entry id="15">
    <source>{f816}聖杯{f817}せいはい{f818}の{f816}中{f817}なか{f818}に{f801}{f816}光{f817}ひかり{f818}が{f816}湧{f817}わ{f818}き{f816}出{f817}だ{f818}した…{f801}{ffff}</source>
    <target>{f816}聖杯{f817}せいはい{f818}の{f816}中{f817}なか{f818}に{f801}{f816}光{f817}ひかり{f818}が{f816}湧{f817}わ{f818}き{f816}出{f817}だ{f818}した…{f801}{ffff}</target>
  </entry>
  <entry id="16">
    <source>{f816}聖杯{f817}せいはい{f818}の{f816}中{f817}なか{f818}に{f801}{f816}光{f817}ひかり{f818}が{f816}湧{f817}わ{f818}き{f816}出{f817}だ{f818}した…{f801}{ffff}</source>
    <target>{f816}聖杯{f817}せいはい{f818}の{f816}中{f817}なか{f818}に{f801}{f816}光{f817}ひかり{f818}が{f816}湧{f817}わ{f818}き{f816}出{f817}だ{f818}した…{f801}{ffff}</target>
  </entry>
  <entry id="17">
    <source>{f816}聖杯{f817}せいはい{f818}の{f816}中{f817}なか{f818}の{f816}光{f817}ひかり{f818}が{f801}{f816}杯{f817}さかずき{f818}を{f816}半分{f817}はんぶん{f818}ほど{f816}満{f817}み{f818}たしている…{f801}{ffff}</source>
    <target>{f816}聖杯{f817}せいはい{f818}の{f816}中{f817}なか{f818}の{f816}光{f817}ひかり{f818}が{f801}{f816}杯{f817}さかずき{f818}を{f816}半分{f817}はんぶん{f818}ほど{f816}満{f817}み{f818}たしている…{f801}{ffff}</target>
  </entry>
  <entry id="18">
    <source>{f816}聖杯{f817}せいはい{f818}の{f816}中{f817}なか{f818}に{f801}{f816}光{f817}ひかり{f818}が{f816}湧{f817}わ{f818}き{f816}出{f817}だ{f818}した…{f801}{ffff}</source>
    <target>{f816}聖杯{f817}せいはい{f818}の{f816}中{f817}なか{f818}に{f801}{f816}光{f817}ひかり{f818}が{f816}湧{f817}わ{f818}き{f816}出{f817}だ{f818}した…{f801}{ffff}</target>
  </entry>
  <entry id="19">
    <source>{f816}聖杯{f817}せいはい{f818}に{f816}湧{f817}わ{f818}き{f816}出{f817}だ{f818}した{f816}光{f817}ひかり{f818}が{f801}{f816}杯{f817}さかずき{f818}を もう{f816}少{f817}すこ{f818}しで{f816}満{f817}み{f818}たしそうだ…{f801}{ffff}</source>
    <target>{f816}聖杯{f817}せいはい{f818}に{f816}湧{f817}わ{f818}き{f816}出{f817}だ{f818}した{f816}光{f817}ひかり{f818}が{f801}{f816}杯{f817}さかずき{f818}を もう{f816}少{f817}すこ{f818}しで{f816}満{f817}み{f818}たしそうだ…{f801}{ffff}</target>
  </entry>
  <entry id="20">
    <source>{f812}前歯が折れた男{0000}{f87a}{2e00}{f813}{0000}{0000}{ad22}{0400}…おぅコラぁ なに{f816}見{f817}み{f818}とんじゃい{f801}{f802}{f813}{0000}{0000}{ae22}{0400}{f816}阿修羅{f817}あしゅら{f818}{f816}会{f817}かい{f818}がなくなったっつってもよぉ{f801}てめぇみたいなガキに{f816}舐{f817}な{f818}められ…{f801}{f802}{f813}{0000}{0000}{af22}{0400}…あん?{f801}{ffff}</source>
    <target>{f812}前歯が折れた男{0000}{f87a}{2e00}{f813}{0000}{0000}{ad22}{0400}…おぅコラぁ なに{f816}見{f817}み{f818}とんじゃい{f801}{f802}{f813}{0000}{0000}{ae22}{0400}{f816}阿修羅{f817}あしゅら{f818}{f816}会{f817}かい{f818}がなくなったっつってもよぉ{f801}てめぇみたいなガキに{f816}舐{f817}な{f818}められ…{f801}{f802}{f813}{0000}{0000}{af22}{0400}…あん?{f801}{ffff}</target>
  </entry>
  <entry id="21">
    <source>{f816}前歯{f817}まえば{f818}が{f816}折{f817}お{f818}れた{f816}男{f817}おとこ{f818}が{f843}{0000}を{f801}{f816}舐{f817}な{f818}めるように{f816}見{f817}み{f818}ている…{f801}{ffff}</source>
    <target>{f816}前歯{f817}まえば{f818}が{f816}折{f817}お{f818}れた{f816}男{f817}おとこ{f818}が{f843}{0000}を{f801}{f816}舐{f817}な{f818}めるように{f816}見{f817}み{f818}ている…{f801}{ffff}</target>
  </entry>
  <entry id="22">
    <source>{f812}前歯が折れた男{0000}{f87a}{2e00}{f813}{0000}{0000}{b022}{0400}…あ…あんた もしかして…{f801}{f816}噂{f817}うわさ{f818}の{f843}{0000}かい?{f801}{f802}{f813}{0000}{0000}{b122}{0400}…やっぱり そうだ!{f801}{f816}俺{f817}おれ{f818}の{f816}連{f817}つ{f818}れが あんたのファンなんだッ!{f801}{ffff}</source>
    <target>{f812}前歯が折れた男{0000}{f87a}{2e00}{f813}{0000}{0000}{b022}{0400}…あ…あんた もしかして…{f801}{f816}噂{f817}うわさ{f818}の{f843}{0000}かい?{f801}{f802}{f813}{0000}{0000}{b122}{0400}…やっぱり そうだ!{f801}{f816}俺{f817}おれ{f818}の{f816}連{f817}つ{f818}れが あんたのファンなんだッ!{f801}{ffff}</target>
  </entry>
  <entry id="23">
    <source>{f812}前歯が折れた男{0000}{f87a}{2e00}{f813}{0000}{0000}{b222}{0400}おぉい {f816}皆{f817}みんな{f818} {f816}来{f817}き{f818}てみろや{f801}{f843}{0000}{f816}様{f817}さま{f818}だぜ{f801}{ffff}</source>
    <target>{f812}前歯が折れた男{0000}{f87a}{2e00}{f813}{0000}{0000}{b222}{0400}おぉい {f816}皆{f817}みんな{f818} {f816}来{f817}き{f818}てみろや{f801}{f843}{0000}{f816}様{f817}さま{f818}だぜ{f801}{ffff}</target>
  </entry>
  <entry id="24">
    <source>{f812}男の声{0000}{f813}{0000}{0000}{b322}{0400}うそ? {f843}{0000}…?{f801}{ffff}</source>
    <target>{f812}男の声{0000}{f813}{0000}{0000}{b322}{0400}うそ? {f843}{0000}…?{f801}{ffff}</target>
  </entry>
  <entry id="25">
    <source>{f812}女の声{0000}{f813}{0000}{0000}{b422}{0400}{f843}{0000}が{f801}{f816}新宿{f817}しんじゅく{f818}にいるの…?{f801}{ffff}</source>
    <target>{f812}女の声{0000}{f813}{0000}{0000}{b422}{0400}{f843}{0000}が{f801}{f816}新宿{f817}しんじゅく{f818}にいるの…?{f801}{ffff}</target>
  </entry>
  <entry id="26">
    <source>{f843}{0000}の{f816}噂{f817}うわさ{f818}を{f816}聞{f817}き{f818}きつけ{f801}{f816}地下街{f817}ちかがい{f818}の{f816}人々{f817}ひとびと{f818}が{f816}集{f817}あつ{f818}まってきた{f801}{ffff}</source>
    <target>{f843}{0000}の{f816}噂{f817}うわさ{f818}を{f816}聞{f817}き{f818}きつけ{f801}{f816}地下街{f817}ちかがい{f818}の{f816}人々{f817}ひとびと{f818}が{f816}集{f817}あつ{f818}まってきた{f801}{ffff}</target>
  </entry>
  <entry id="27">
    <source>{f812}イザボー{0000}{f87a}{0500}{f87b}{0500}{0600}{0100}{0100}{f813}{0000}{0000}{b522}{0400}…{f843}{0000} {f816}注目{f817}ちゅうもく{f818}の{f816}的{f817}まと{f818}ね{f801}{ffff}</source>
    <target>{f812}イザボー{0000}{f87a}{0500}{f87b}{0500}{0600}{0100}{0100}{f813}{0000}{0000}{b522}{0400}…{f843}{0000} {f816}注目{f817}ちゅうもく{f818}の{f816}的{f817}まと{f818}ね{f801}{ffff}</target>
  </entry>
  <entry id="28">
    <source>{f812}女の声{0000}{f813}{0000}{0000}{b622}{0400}この{f816}人{f817}ひと{f818}でしょ?{f801}{f816}悪魔{f817}あくま{f818}を{f816}倒{f817}たお{f818}してくれる{f816}人{f817}ひと{f818}{f801}{ffff}</source>
    <target>{f812}女の声{0000}{f813}{0000}{0000}{b622}{0400}この{f816}人{f817}ひと{f818}でしょ?{f801}{f816}悪魔{f817}あくま{f818}を{f816}倒{f817}たお{f818}してくれる{f816}人{f817}ひと{f818}{f801}{ffff}</target>
  </entry>
  <entry id="29">
    <source>{f812}男の声{0000}{f813}{0000}{0000}{b722}{0400}いつも{f816}掲示板{f817}けいじばん{f818} {f816}見{f817}み{f818}ているよ{f801}{f802}{f813}{0000}{0000}{b822}{0400}{f816}君{f817}きみ{f818}の{f816}活躍{f817}かつやく{f818}を{f816}見{f817}み{f818}ていると{f801}『がんばらなきゃ』って{f816}希望{f817}きぼう{f818}が{f816}湧{f817}わ{f818}くんだ{f801}{ffff}</source>
    <target>{f812}男の声{0000}{f813}{0000}{0000}{b722}{0400}いつも{f816}掲示板{f817}けいじばん{f818} {f816}見{f817}み{f818}ているよ{f801}{f802}{f813}{0000}{0000}{b822}{0400}{f816}君{f817}きみ{f818}の{f816}活躍{f817}かつやく{f818}を{f816}見{f817}み{f818}ていると{f801}『がんばらなきゃ』って{f816}希望{f817}きぼう{f818}が{f816}湧{f817}わ{f818}くんだ{f801}{ffff}</target>
  </entry>
  <entry id="30">
    <source>エラーです{f801}{ffff}</source>
    <target>エラーです{f801}{ffff}</target>
  </entry>
  <entry id="31">
    <source>{f816}聖杯{f817}せいはい{f818}の{f816}中{f817}なか{f818}に{f801}{f816}光{f817}ひかり{f818}が{f816}湧{f817}わ{f818}き{f816}出{f817}だ{f818}した…{f801}{ffff}</source>
    <target>{f816}聖杯{f817}せいはい{f818}の{f816}中{f817}なか{f818}に{f801}{f816}光{f817}ひかり{f818}が{f816}湧{f817}わ{f818}き{f816}出{f817}だ{f818}した…{f801}{ffff}</target>
  </entry>
  <entry id="32">
    <source>{f816}聖杯{f817}せいはい{f818}の{f816}中{f817}なか{f818}に{f801}{f816}光{f817}ひかり{f818}が{f816}湧{f817}わ{f818}き{f816}出{f817}だ{f818}した…{f801}{ffff}</source>
    <target>{f816}聖杯{f817}せいはい{f818}の{f816}中{f817}なか{f818}に{f801}{f816}光{f817}ひかり{f818}が{f816}湧{f817}わ{f818}き{f816}出{f817}だ{f818}した…{f801}{ffff}</target>
  </entry>
  <entry id="33">
    <source>{f816}聖杯{f817}せいはい{f818}の{f816}中{f817}なか{f818}の{f816}光{f817}ひかり{f818}が{f801}{f816}杯{f817}さかずき{f818}を{f816}半分{f817}はんぶん{f818}ほど{f816}満{f817}み{f818}たしている…{f801}{ffff}</source>
    <target>{f816}聖杯{f817}せいはい{f818}の{f816}中{f817}なか{f818}の{f816}光{f817}ひかり{f818}が{f801}{f816}杯{f817}さかずき{f818}を{f816}半分{f817}はんぶん{f818}ほど{f816}満{f817}み{f818}たしている…{f801}{ffff}</target>
  </entry>
  <entry id="34">
    <source>{f816}聖杯{f817}せいはい{f818}の{f816}中{f817}なか{f818}に{f801}{f816}光{f817}ひかり{f818}が{f816}湧{f817}わ{f818}き{f816}出{f817}だ{f818}した…{f801}{ffff}</source>
    <target>{f816}聖杯{f817}せいはい{f818}の{f816}中{f817}なか{f818}に{f801}{f816}光{f817}ひかり{f818}が{f816}湧{f817}わ{f818}き{f816}出{f817}だ{f818}した…{f801}{ffff}</target>
  </entry>
  <entry id="35">
    <source>{f816}聖杯{f817}せいはい{f818}に{f816}湧{f817}わ{f818}き{f816}出{f817}だ{f818}した{f816}光{f817}ひかり{f818}が{f801}{f816}杯{f817}さかずき{f818}を もう{f816}少{f817}すこ{f818}しで{f816}満{f817}み{f818}たしそうだ…{f801}{ffff}</source>
    <target>{f816}聖杯{f817}せいはい{f818}に{f816}湧{f817}わ{f818}き{f816}出{f817}だ{f818}した{f816}光{f817}ひかり{f818}が{f801}{f816}杯{f817}さかずき{f818}を もう{f816}少{f817}すこ{f818}しで{f816}満{f817}み{f818}たしそうだ…{f801}{ffff}</target>
  </entry>
  <entry id="36">
    <source>{f812}派手なまつ毛の女{0000}{f87a}{7b00}{f813}{0000}{0000}{b922}{0400}…ねぇ あれ…そうじゃないの?{f801}{f816}絶対{f817}ぜったい{f818}そうだって{f801}{ffff}</source>
    <target>{f812}派手なまつ毛の女{0000}{f87a}{7b00}{f813}{0000}{0000}{b922}{0400}…ねぇ あれ…そうじゃないの?{f801}{f816}絶対{f817}ぜったい{f818}そうだって{f801}{ffff}</target>
  </entry>
  <entry id="37">
    <source>{f812}派手なネイルの女{0000}{f87a}{7a00}{f813}{0000}{0000}{ba22}{0400}んなわけないっしょ…{f801}{ffff}</source>
    <target>{f812}派手なネイルの女{0000}{f87a}{7a00}{f813}{0000}{0000}{ba22}{0400}んなわけないっしょ…{f801}{ffff}</target>
  </entry>
  <entry id="38">
    <source>{f816}派手{f817}はで{f818}なネイルの{f816}女{f817}おんな{f818}が{f816}眉間{f817}みけん{f818}にシワを{f816}寄{f817}よ{f818}せて{f801}{f843}{0000}を{f816}見{f817}み{f818}ている{f801}{ffff}</source>
    <target>{f816}派手{f817}はで{f818}なネイルの{f816}女{f817}おんな{f818}が{f816}眉間{f817}みけん{f818}にシワを{f816}寄{f817}よ{f818}せて{f801}{f843}{0000}を{f816}見{f817}み{f818}ている{f801}{ffff}</target>
  </entry>
  <entry id="39">
    <source>欠番です{f801}{ffff}</source>
    <target>欠番です{f801}{ffff}</target>
  </entry>
  <entry id="40">
    <source>{f812}派手なネイルの女{0000}{f87a}{7a00}欠番です{f801}{ffff}</source>
    <target>{f812}派手なネイルの女{0000}{f87a}{7a00}欠番です{f801}{ffff}</target>
  </entry>
  <entry id="41">
    <source>{f812}派手なまつ毛の女{0000}{f87a}{7b00}欠番です{f801}{ffff}</source>
    <target>{f812}派手なまつ毛の女{0000}{f87a}{7b00}欠番です{f801}{ffff}</target>
  </entry>
  <entry id="42">
    <source>欠番です{f801}{ffff}</source>
    <target>欠番です{f801}{ffff}</target>
  </entry>
  <entry id="43">
    <source>{f812}派手なまつ毛の女{0000}{f87a}{7b00}欠番です{f801}{ffff}</source>
    <target>{f812}派手なまつ毛の女{0000}{f87a}{7b00}欠番です{f801}{ffff}</target>
  </entry>
  <entry id="44">
    <source>{f812}派手なネイルの女{0000}{f87a}{7a00}{f813}{0000}{0000}{bb22}{0400}…うぅわッ マジで{f843}{0000}{f801}すげぇイケてんですけど{f801}{ffff}</source>
    <target>{f812}派手なネイルの女{0000}{f87a}{7a00}{f813}{0000}{0000}{bb22}{0400}…うぅわッ マジで{f843}{0000}{f801}すげぇイケてんですけど{f801}{ffff}</target>
  </entry>
  <entry id="45">
    <source>{f812}女の声{0000}{f813}{0000}{0000}{bc22}{0400}{f843}{0000}だって?{f801}{f816}渋谷{f817}しぶや{f818}に{f816}来{f817}き{f818}てるの?{f801}{ffff}</source>
    <target>{f812}女の声{0000}{f813}{0000}{0000}{bc22}{0400}{f843}{0000}だって?{f801}{f816}渋谷{f817}しぶや{f818}に{f816}来{f817}き{f818}てるの?{f801}{ffff}</target>
  </entry>
  <entry id="46">
    <source>{f812}男の声{0000}{f813}{0000}{0000}{bd22}{0400}ホントだ {f843}{0000}だ{f801}しかも{f816}女{f817}おんな{f818}{f816}連{f817}づ{f818}れかよッ{f801}{ffff}</source>
    <target>{f812}男の声{0000}{f813}{0000}{0000}{bd22}{0400}ホントだ {f843}{0000}だ{f801}しかも{f816}女{f817}おんな{f818}{f816}連{f817}づ{f818}れかよッ{f801}{ffff}</target>
  </entry>
  <entry id="47">
    <source>{f843}{0000}の{f816}噂{f817}うわさ{f818}を{f816}聞{f817}き{f818}きつけ{f801}{f816}地下街{f817}ちかがい{f818}の{f816}人々{f817}ひとびと{f818}が{f816}集{f817}あつ{f818}まってきた{f801}{ffff}</source>
    <target>{f843}{0000}の{f816}噂{f817}うわさ{f818}を{f816}聞{f817}き{f818}きつけ{f801}{f816}地下街{f817}ちかがい{f818}の{f816}人々{f817}ひとびと{f818}が{f816}集{f817}あつ{f818}まってきた{f801}{ffff}</target>
  </entry>
  <entry id="48">
    <source>{f812}イザボー{0000}{f87a}{0500}{f87b}{0500}{0100}{0100}{0100}{f813}{0000}{0000}{be22}{0400}なんだか{f816}急{f817}きゅう{f818}に{f816}賑{f817}にぎ{f818}やかになったわね{f801}{ffff}</source>
    <target>{f812}イザボー{0000}{f87a}{0500}{f87b}{0500}{0100}{0100}{0100}{f813}{0000}{0000}{be22}{0400}なんだか{f816}急{f817}きゅう{f818}に{f816}賑{f817}にぎ{f818}やかになったわね{f801}{ffff}</target>
  </entry>
  <entry id="49">
    <source>{f812}男の声{0000}{f813}{0000}{0000}{bf22}{0400}{f816}悪魔{f817}あくま{f818} {f816}増{f817}ふ{f818}えすぎなんだよ{f801}{f816}殺{f817}や{f818}っちゃってよ {f843}{0000}!{f801}{ffff}</source>
    <target>{f812}男の声{0000}{f813}{0000}{0000}{bf22}{0400}{f816}悪魔{f817}あくま{f818} {f816}増{f817}ふ{f818}えすぎなんだよ{f801}{f816}殺{f817}や{f818}っちゃってよ {f843}{0000}!{f801}{ffff}</target>
  </entry>
  <entry id="50">
    <source>{f812}女の声{0000}{f813}{0000}{0000}{c022}{0400}うちらだってさ {f816}生{f817}い{f818}きていれば{f801}こんなイケメンと{f816}付{f817}つ{f818}き{f816}合{f817}あ{f818}えるかもだよね{f801}{f802}{f813}{0000}{0000}{c122}{0400}なんだか{f816}希望{f817}きぼう{f818}が{f816}湧{f817}わ{f818}いてきちゃった{f801}{ffff}</source>
    <target>{f812}女の声{0000}{f813}{0000}{0000}{c022}{0400}うちらだってさ {f816}生{f817}い{f818}きていれば{f801}こんなイケメンと{f816}付{f817}つ{f818}き{f816}合{f817}あ{f818}えるかもだよね{f801}{f802}{f813}{0000}{0000}{c122}{0400}なんだか{f816}希望{f817}きぼう{f818}が{f816}湧{f817}わ{f818}いてきちゃった{f801}{ffff}</target>
  </entry>
  <entry id="51">
    <source>エラーです{f801}{ffff}</source>
    <target>エラーです{f801}{ffff}</target>
  </entry>
  <entry id="52">
    <source>{f816}聖杯{f817}せいはい{f818}の{f816}中{f817}なか{f818}に{f801}{f816}光{f817}ひかり{f818}が{f816}湧{f817}わ{f818}き{f816}出{f817}だ{f818}した…{f801}{ffff}</source>
    <target>{f816}聖杯{f817}せいはい{f818}の{f816}中{f817}なか{f818}に{f801}{f816}光{f817}ひかり{f818}が{f816}湧{f817}わ{f818}き{f816}出{f817}だ{f818}した…{f801}{ffff}</target>
  </entry>
  <entry id="53">
    <source>{f816}聖杯{f817}せいはい{f818}の{f816}中{f817}なか{f818}に{f801}{f816}光{f817}ひかり{f818}が{f816}湧{f817}わ{f818}き{f816}出{f817}だ{f818}した…{f801}{ffff}</source>
    <target>{f816}聖杯{f817}せいはい{f818}の{f816}中{f817}なか{f818}に{f801}{f816}光{f817}ひかり{f818}が{f816}湧{f817}わ{f818}き{f816}出{f817}だ{f818}した…{f801}{ffff}</target>
  </entry>
  <entry id="54">
    <source>{f816}聖杯{f817}せいはい{f818}の{f816}中{f817}なか{f818}の{f816}光{f817}ひかり{f818}が{f801}{f816}杯{f817}さかずき{f818}を{f816}半分{f817}はんぶん{f818}ほど{f816}満{f817}み{f818}たしている…{f801}{ffff}</source>
    <target>{f816}聖杯{f817}せいはい{f818}の{f816}中{f817}なか{f818}の{f816}光{f817}ひかり{f818}が{f801}{f816}杯{f817}さかずき{f818}を{f816}半分{f817}はんぶん{f818}ほど{f816}満{f817}み{f818}たしている…{f801}{ffff}</target>
  </entry>
  <entry id="55">
    <source>{f816}聖杯{f817}せいはい{f818}の{f816}中{f817}なか{f818}に{f801}{f816}光{f817}ひかり{f818}が{f816}湧{f817}わ{f818}き{f816}出{f817}だ{f818}した…{f801}{ffff}</source>
    <target>{f816}聖杯{f817}せいはい{f818}の{f816}中{f817}なか{f818}に{f801}{f816}光{f817}ひかり{f818}が{f816}湧{f817}わ{f818}き{f816}出{f817}だ{f818}した…{f801}{ffff}</target>
  </entry>
  <entry id="56">
    <source>{f816}聖杯{f817}せいはい{f818}に{f816}湧{f817}わ{f818}き{f816}出{f817}だ{f818}した{f816}光{f817}ひかり{f818}が{f801}{f816}杯{f817}さかずき{f818}を もう{f816}少{f817}すこ{f818}しで{f816}満{f817}み{f818}たしそうだ…{f801}{ffff}</source>
    <target>{f816}聖杯{f817}せいはい{f818}に{f816}湧{f817}わ{f818}き{f816}出{f817}だ{f818}した{f816}光{f817}ひかり{f818}が{f801}{f816}杯{f817}さかずき{f818}を もう{f816}少{f817}すこ{f818}しで{f816}満{f817}み{f818}たしそうだ…{f801}{ffff}</target>
  </entry>
  <entry id="57">
    <source>{f812}カタコトの女{0000}{f87a}{3e00}{f813}{0000}{0000}{c222}{0400}…お{f816}兄{f817}にい{f818}さん いい{f816}男{f817}おとこ{f818}ネ{f801}マッサージ…ん?{f801}{f802}{f813}{0000}{0000}{c322}{0400}お{f816}兄{f817}にい{f818}さん もしかして…{f801}{f843}{0000}?{f801}{ffff}</source>
    <target>{f812}カタコトの女{0000}{f87a}{3e00}{f813}{0000}{0000}{c222}{0400}…お{f816}兄{f817}にい{f818}さん いい{f816}男{f817}おとこ{f818}ネ{f801}マッサージ…ん?{f801}{f802}{f813}{0000}{0000}{c322}{0400}お{f816}兄{f817}にい{f818}さん もしかして…{f801}{f843}{0000}?{f801}{ffff}</target>
  </entry>
  <entry id="58">
    <source>カタコトの{f816}女{f817}おんな{f818}が{f843}{0000}を{f801}{f816}舐{f817}な{f818}めるように{f816}見{f817}み{f818}ている…{f801}{ffff}</source>
    <target>カタコトの{f816}女{f817}おんな{f818}が{f843}{0000}を{f801}{f816}舐{f817}な{f818}めるように{f816}見{f817}み{f818}ている…{f801}{ffff}</target>
  </entry>
  <entry id="59">
    <source>{f812}カタコトの女{0000}{f87a}{3e00}{f813}{0000}{0000}{c422}{0400}きっと そうねッ{f801}お{f816}客{f817}きゃく{f818}さんに{f816}写真{f817}しゃしん{f818} {f816}見{f817}み{f818}してもらったよ{f801}{f802}{f813}{0000}{0000}{c522}{0400}いっぺん{f816}会{f817}あ{f818}いたかったよ{f801}{f816}東京{f817}とうきょう{f818}の{f816}英雄{f817}えいゆう{f818}なんでしょ?{f801}{ffff}</source>
    <target>{f812}カタコトの女{0000}{f87a}{3e00}{f813}{0000}{0000}{c422}{0400}きっと そうねッ{f801}お{f816}客{f817}きゃく{f818}さんに{f816}写真{f817}しゃしん{f818} {f816}見{f817}み{f818}してもらったよ{f801}{f802}{f813}{0000}{0000}{c522}{0400}いっぺん{f816}会{f817}あ{f818}いたかったよ{f801}{f816}東京{f817}とうきょう{f818}の{f816}英雄{f817}えいゆう{f818}なんでしょ?{f801}{ffff}</target>
  </entry>
  <entry id="60">
    <source>{f812}男の声{0000}{f813}{0000}{0000}{c622}{0400}…うそ? {f843}{0000}?{f801}{ffff}</source>
    <target>{f812}男の声{0000}{f813}{0000}{0000}{c622}{0400}…うそ? {f843}{0000}?{f801}{ffff}</target>
  </entry>
  <entry id="61">
    <source>{f812}女の声{0000}{f813}{0000}{0000}{c722}{0400}…{f816}本当{f817}ほんとう{f818}だ {f843}{0000}だ{f801}{f816}池袋{f817}いけぶくろ{f818}に{f816}来{f817}き{f818}てたんだ{f801}{ffff}</source>
    <target>{f812}女の声{0000}{f813}{0000}{0000}{c722}{0400}…{f816}本当{f817}ほんとう{f818}だ {f843}{0000}だ{f801}{f816}池袋{f817}いけぶくろ{f818}に{f816}来{f817}き{f818}てたんだ{f801}{ffff}</target>
  </entry>
  <entry id="62">
    <source>{f843}{0000}の{f816}噂{f817}うわさ{f818}を{f816}聞{f817}き{f818}きつけ{f801}{f816}地下街{f817}ちかがい{f818}の{f816}人々{f817}ひとびと{f818}が{f816}集{f817}あつ{f818}まってきた{f801}{ffff}</source>
    <target>{f843}{0000}の{f816}噂{f817}うわさ{f818}を{f816}聞{f817}き{f818}きつけ{f801}{f816}地下街{f817}ちかがい{f818}の{f816}人々{f817}ひとびと{f818}が{f816}集{f817}あつ{f818}まってきた{f801}{ffff}</target>
  </entry>
  <entry id="63">
    <source>{f812}女の声{0000}{f813}{0000}{0000}{c922}{0400}{f816}素敵{f817}すてき{f818}よ {f816}素敵{f817}すてき{f818}{f801}{f816}他{f817}ほか{f818}に{f816}言葉{f817}ことば{f818}が{f816}見{f817}み{f818}つからないくらい{f816}素敵{f817}すてき{f818}ッ{f801}{ffff}</source>
    <target>{f812}女の声{0000}{f813}{0000}{0000}{c922}{0400}{f816}素敵{f817}すてき{f818}よ {f816}素敵{f817}すてき{f818}{f801}{f816}他{f817}ほか{f818}に{f816}言葉{f817}ことば{f818}が{f816}見{f817}み{f818}つからないくらい{f816}素敵{f817}すてき{f818}ッ{f801}{ffff}</target>
  </entry>
  <entry id="64">
    <source>{f812}男の声{0000}{f813}{0000}{0000}{ca22}{0400}あんたと{f816}同{f817}おな{f818}じ{f816}空気{f817}くうき{f818}を{f816}吸{f817}す{f818}ってるってだけで{f801}{f816}誇{f817}ほこ{f818}りに{f816}思{f817}おも{f818}えてくるんだ{f801}{f802}{f813}{0000}{0000}{cb22}{0400}{f816}俺{f817}おれ{f818} この{f816}東京{f817}とうきょう{f818}に{f816}希望{f817}きぼう{f818}を{f816}見{f817}み{f818}たぜッ{f801}{ffff}</source>
    <target>{f812}男の声{0000}{f813}{0000}{0000}{ca22}{0400}あんたと{f816}同{f817}おな{f818}じ{f816}空気{f817}くうき{f818}を{f816}吸{f817}す{f818}ってるってだけで{f801}{f816}誇{f817}ほこ{f818}りに{f816}思{f817}おも{f818}えてくるんだ{f801}{f802}{f813}{0000}{0000}{cb22}{0400}{f816}俺{f817}おれ{f818} この{f816}東京{f817}とうきょう{f818}に{f816}希望{f817}きぼう{f818}を{f816}見{f817}み{f818}たぜッ{f801}{ffff}</target>
  </entry>
  <entry id="65">
    <source>エラーです{f801}{ffff}</source>
    <target>エラーです{f801}{ffff}</target>
  </entry>
  <entry id="66">
    <source>{f816}聖杯{f817}せいはい{f818}の{f816}中{f817}なか{f818}に{f801}{f816}光{f817}ひかり{f818}が{f816}湧{f817}わ{f818}き{f816}出{f817}だ{f818}した…{f801}{ffff}</source>
    <target>{f816}聖杯{f817}せいはい{f818}の{f816}中{f817}なか{f818}に{f801}{f816}光{f817}ひかり{f818}が{f816}湧{f817}わ{f818}き{f816}出{f817}だ{f818}した…{f801}{ffff}</target>
  </entry>
  <entry id="67">
    <source>{f816}聖杯{f817}せいはい{f818}の{f816}中{f817}なか{f818}に{f801}{f816}光{f817}ひかり{f818}が{f816}湧{f817}わ{f818}き{f816}出{f817}だ{f818}した…{f801}{ffff}</source>
    <target>{f816}聖杯{f817}せいはい{f818}の{f816}中{f817}なか{f818}に{f801}{f816}光{f817}ひかり{f818}が{f816}湧{f817}わ{f818}き{f816}出{f817}だ{f818}した…{f801}{ffff}</target>
  </entry>
  <entry id="68">
    <source>{f816}聖杯{f817}せいはい{f818}の{f816}中{f817}なか{f818}の{f816}光{f817}ひかり{f818}が{f801}{f816}杯{f817}さかずき{f818}を{f816}半分{f817}はんぶん{f818}ほど{f816}満{f817}み{f818}たしている…{f801}{ffff}</source>
    <target>{f816}聖杯{f817}せいはい{f818}の{f816}中{f817}なか{f818}の{f816}光{f817}ひかり{f818}が{f801}{f816}杯{f817}さかずき{f818}を{f816}半分{f817}はんぶん{f818}ほど{f816}満{f817}み{f818}たしている…{f801}{ffff}</target>
  </entry>
  <entry id="69">
    <source>{f816}聖杯{f817}せいはい{f818}の{f816}中{f817}なか{f818}に{f801}{f816}光{f817}ひかり{f818}が{f816}湧{f817}わ{f818}き{f816}出{f817}だ{f818}した…{f801}{ffff}</source>
    <target>{f816}聖杯{f817}せいはい{f818}の{f816}中{f817}なか{f818}に{f801}{f816}光{f817}ひかり{f818}が{f816}湧{f817}わ{f818}き{f816}出{f817}だ{f818}した…{f801}{ffff}</target>
  </entry>
  <entry id="70">
    <source>{f816}聖杯{f817}せいはい{f818}に{f816}湧{f817}わ{f818}き{f816}出{f817}だ{f818}した{f816}光{f817}ひかり{f818}が{f801}{f816}杯{f817}さかずき{f818}を もう{f816}少{f817}すこ{f818}しで{f816}満{f817}み{f818}たしそうだ…{f801}{ffff}</source>
    <target>{f816}聖杯{f817}せいはい{f818}に{f816}湧{f817}わ{f818}き{f816}出{f817}だ{f818}した{f816}光{f817}ひかり{f818}が{f801}{f816}杯{f817}さかずき{f818}を もう{f816}少{f817}すこ{f818}しで{f816}満{f817}み{f818}たしそうだ…{f801}{ffff}</target>
  </entry>
  <entry id="71">
    <source>{f816}聖杯{f817}せいはい{f818}の{f816}中{f817}なか{f818}に{f801}{f816}光{f817}ひかり{f818}が{f816}湧{f817}わ{f818}き{f816}出{f817}だ{f818}した…{f801}{ffff}</source>
    <target>{f816}聖杯{f817}せいはい{f818}の{f816}中{f817}なか{f818}に{f801}{f816}光{f817}ひかり{f818}が{f816}湧{f817}わ{f818}き{f816}出{f817}だ{f818}した…{f801}{ffff}</target>
  </entry>
  <entry id="72">
    <source>{f816}聖杯{f817}せいはい{f818}の{f816}中{f817}なか{f818}に{f801}{f816}光{f817}ひかり{f818}が{f816}満{f817}み{f818}ち{f816}満{f817}み{f818}ちている…{f801}{ffff}</source>
    <target>{f816}聖杯{f817}せいはい{f818}の{f816}中{f817}なか{f818}に{f801}{f816}光{f817}ひかり{f818}が{f816}満{f817}み{f818}ち{f816}満{f817}み{f818}ちている…{f801}{ffff}</target>
  </entry>
  <entry id="73">
    <source>{f812}イザボー{0000}{f87a}{0500}{f87b}{0500}{0100}{0100}{0100}{f813}{0000}{0000}{cc22}{0400}…ん? {f816}何{f817}なに{f818}かしら…?{f801}{ffff}</source>
    <target>{f812}イザボー{0000}{f87a}{0500}{f87b}{0500}{0100}{0100}{0100}{f813}{0000}{0000}{cc22}{0400}…ん? {f816}何{f817}なに{f818}かしら…?{f801}{ffff}</target>
  </entry>
  <entry id="74">
    <source>{f816}聖杯{f817}せいはい{f818}の{f816}中{f817}なか{f818}で{f816}光{f817}ひかり{f818}がひとつにまとまり{f801}{f816}形{f817}かたち{f818}を{f816}成{f817}な{f818}していく…{f801}{ffff}</source>
    <target>{f816}聖杯{f817}せいはい{f818}の{f816}中{f817}なか{f818}で{f816}光{f817}ひかり{f818}がひとつにまとまり{f801}{f816}形{f817}かたち{f818}を{f816}成{f817}な{f818}していく…{f801}{ffff}</target>
  </entry>
  <entry id="75">
    <source>{f812}イザボー{0000}{f87a}{0500}{f87b}{0500}{0600}{0100}{0100}{f813}{0000}{0000}{cd22}{0400}…なんて{f816}温{f817}あたた{f818}かい{f816}光{f817}ひかり{f818}{f801}{f816}優{f817}やさ{f818}しくて でもどこか{f816}儚{f817}はかな{f818}げで…{f801}{ffff}</source>
    <target>{f812}イザボー{0000}{f87a}{0500}{f87b}{0500}{0600}{0100}{0100}{f813}{0000}{0000}{cd22}{0400}…なんて{f816}温{f817}あたた{f818}かい{f816}光{f817}ひかり{f818}{f801}{f816}優{f817}やさ{f818}しくて でもどこか{f816}儚{f817}はかな{f818}げで…{f801}{ffff}</target>
  </entry>
  <entry id="76">
    <source>{f812}イザボー{0000}{f87a}{0500}{f87b}{0500}{0a00}{0100}{0100}{f813}{0000}{0000}{ce22}{0400}これがマサカドの{f816}言{f817}い{f818}う{f801}{f816}希望{f817}きぼう{f818}の{f816}大魂{f817}おおだま{f818}ではないかしら…?{f801}{ffff}</source>
    <target>{f812}イザボー{0000}{f87a}{0500}{f87b}{0500}{0a00}{0100}{0100}{f813}{0000}{0000}{ce22}{0400}これがマサカドの{f816}言{f817}い{f818}う{f801}{f816}希望{f817}きぼう{f818}の{f816}大魂{f817}おおだま{f818}ではないかしら…?{f801}{ffff}</target>
  </entry>
  <entry id="102">
    <source>{f812}店主{0000}{f87a}{1800}{f813}{0000}{0000}{9d22}{0400}『チャンピオン』か…{f801}{f802}{f813}{0000}{0000}{9e22}{0400}こんな{f816}暗{f817}くら{f818}い{f816}時代{f817}じだい{f818}に{f801}{f816}希望{f817}きぼう{f818}が{f816}湧{f817}わ{f818}く{f816}響{f817}ひび{f818}きじゃないの{f801}{ffff}</source>
    <target>{f812}店主{0000}{f87a}{1800}{f813}{0000}{0000}{9d22}{0400}『チャンピオン』か…{f801}{f802}{f813}{0000}{0000}{9e22}{0400}こんな{f816}暗{f817}くら{f818}い{f816}時代{f817}じだい{f818}に{f801}{f816}希望{f817}きぼう{f818}が{f816}湧{f817}わ{f818}く{f816}響{f817}ひび{f818}きじゃないの{f801}{ffff}</target>
  </entry>
  <entry id="103">
    <source>{f812}バロウズ{0000}{f87a}{0200}{f813}{0000}{0000}{bf1a}{0600}クエスト いい{f816}感{f817}かん{f818}じに{f816}進{f817}すす{f818}んでるみたいね{f801}{ffff}</source>
    <target>{f812}バロウズ{0000}{f87a}{0200}{f813}{0000}{0000}{bf1a}{0600}クエスト いい{f816}感{f817}かん{f818}じに{f816}進{f817}すす{f818}んでるみたいね{f801}{ffff}</target>
  </entry>
  <entry id="162">
    <source>{f812}イザボー{0000}{f87a}{0500}{f87b}{0500}{0600}{0100}{0100}{f813}{0000}{0000}{c822}{0400}{f843}{0000}の{f816}名前{f817}なまえ{f818}が{f816}出{f817}で{f818}ただけで{f801}こんなに{f816}騒{f817}さわ{f818}ぎになるだなんて…{f801}{ffff}</source>
    <target>{f812}イザボー{0000}{f87a}{0500}{f87b}{0500}{0600}{0100}{0100}{f813}{0000}{0000}{c822}{0400}{f843}{0000}の{f816}名前{f817}なまえ{f818}が{f816}出{f817}で{f818}ただけで{f801}こんなに{f816}騒{f817}さわ{f818}ぎになるだなんて…{f801}{ffff}</target>
  </entry>
  <entry id="176">
    <source>{f816}聖杯{f817}せいはい{f818}は{f816}満{f817}み{f818}たされた{f801}{ffff}</source>
    <target>{f816}聖杯{f817}せいはい{f818}は{f816}満{f817}み{f818}たされた{f801}{ffff}</target>
  </entry>
  <entry id="202">
    <source>{f812}イザボー{0000}{f87a}{0500}{f87b}{0500}{0a00}{0100}{0100}{f813}{0000}{0000}{9f22}{0400}あ…{f816}見{f817}み{f818}て{f801}{f816}聖杯{f817}せいはい{f818}に{f816}何{f817}なに{f818}か{f816}湧{f817}わ{f818}き{f816}出{f817}だ{f818}したわ…{f801}{ffff}</source>
    <target>{f812}イザボー{0000}{f87a}{0500}{f87b}{0500}{0a00}{0100}{0100}{f813}{0000}{0000}{9f22}{0400}あ…{f816}見{f817}み{f818}て{f801}{f816}聖杯{f817}せいはい{f818}に{f816}何{f817}なに{f818}か{f816}湧{f817}わ{f818}き{f816}出{f817}だ{f818}したわ…{f801}{ffff}</target>
  </entry>
  <entry id="276">
    <source>{f812}バロウズ{0000}{f87a}{0200}{f813}{0000}{0000}{bf1a}{0600}クエスト いい{f816}感{f817}かん{f818}じに{f816}進{f817}すす{f818}んでるみたいね{f801}{ffff}</source>
    <target>{f812}バロウズ{0000}{f87a}{0200}{f813}{0000}{0000}{bf1a}{0600}クエスト いい{f816}感{f817}かん{f818}じに{f816}進{f817}すす{f818}んでるみたいね{f801}{ffff}</target>
  </entry>
  <entry id="302">
    <source>{f816}聖杯{f817}せいはい{f818}の{f816}中{f817}なか{f818}に{f801}ほんの{f816}少{f817}すこ{f818}し{f816}光{f817}ひかり{f818}が{f816}湧{f817}わ{f818}き{f816}出{f817}だ{f818}した…{f801}{ffff}</source>
    <target>{f816}聖杯{f817}せいはい{f818}の{f816}中{f817}なか{f818}に{f801}ほんの{f816}少{f817}すこ{f818}し{f816}光{f817}ひかり{f818}が{f816}湧{f817}わ{f818}き{f816}出{f817}だ{f818}した…{f801}{ffff}</target>
  </entry>
</mbm>