<mbm>
  <entry id="0">
    <source>{f812}男性人畜{0000}{f87a}{6b00}{f813}{0100}{0000}{cb27}{0600}恶魔就是把东京搞乱的罪魁祸首,{f801}和那些家伙…合体?!{f801}{f802}怎么会有那种选择?{f801}我无法理解…{f801}{ffff}</source>
    <target>{f812}男性人畜{0000}{f87a}{6b00}{f813}{0100}{0000}{cb27}{0600}恶魔就是把东京搞乱的罪魁祸首,{f801}和那些家伙…合体?!{f801}{f802}怎么会有那种选择?{f801}我无法理解…{f801}{ffff}</target>
  </entry>
  <entry id="1">
    <source>{f812}男性人畜{0000}{f87a}{6b00}{f813}{0100}{0000}{cb27}{0600}东京变成这样是健二的错,{f801}都是因为他忤逆神迹…!{f801}{f802}…嗯?『四大天使』?{f801}说什么傻话,天使都被健二给杀了。{f801}{f802}…但如果真的有四大天使的话,{f801}会不会恶魔就已经从东京消失了呢…?{f801}{ffff}</source>
    <target>{f812}男性人畜{0000}{f87a}{6b00}{f813}{0100}{0000}{cb27}{0600}东京变成这样是健二的错,{f801}都是因为他忤逆神迹…!{f801}{f802}…嗯?『四大天使』?{f801}说什么傻话,天使都被健二给杀了。{f801}{f802}…但如果真的有四大天使的话,{f801}会不会恶魔就已经从东京消失了呢…?{f801}{ffff}</target>
  </entry>
  <entry id="2">
    <source>{f812}女恶魔人{0000}{f87a}{9400}{f813}{0100}{0000}蘰{0600}…你胳膊上那东西里安装的{f801}是恶魔召唤程序吧?{f801}{f802}还留着啊,真不错。{f801}…啊?在『仪式』上得到的?{f801}{f802}不是下载的吗?{f801}和我之前那个不一样吗…?{f801}{ffff}</source>
    <target>{f812}女恶魔人{0000}{f87a}{9400}{f813}{0100}{0000}蘰{0600}…你胳膊上那东西里安装的{f801}是恶魔召唤程序吧?{f801}{f802}还留着啊,真不错。{f801}…啊?在『仪式』上得到的?{f801}{f802}不是下载的吗?{f801}和我之前那个不一样吗…?{f801}{ffff}</target>
  </entry>
  <entry id="3">
    <source>{f812}女恶魔人{0000}{f87a}{9400}{f813}{0100}{0000}蘰{0600}呐,外来者小哥,{f801}我们之前是不是在哪里见过?{f801}{f802}其实我是原恶魔讨伐队成员,{f801}虽然那是我还是人类时候的事了。{f801}{f802}既然你有恶魔召唤程序,{f801}说明以前也在恶魔讨伐队待过吧…?{f801}{ffff}</source>
    <target>{f812}女恶魔人{0000}{f87a}{9400}{f813}{0100}{0000}蘰{0600}呐,外来者小哥,{f801}我们之前是不是在哪里见过?{f801}{f802}其实我是原恶魔讨伐队成员,{f801}虽然那是我还是人类时候的事了。{f801}{f802}既然你有恶魔召唤程序,{f801}说明以前也在恶魔讨伐队待过吧…?{f801}{ffff}</target>
  </entry>
  <entry id="4">
    <source>{f812}女恶魔人{0000}{f87a}{9400}{f813}{0100}{0000}馥{0600}健二在你们这么大的时候{f801}原来也是恶魔讨伐队的成员。{f801}{f802}他最初是为了保护东京,才加入{f801}恶魔讨伐队和恶魔战斗的…{f801}{f802}但是,恶魔出现在东京,{f801}其实是神的意思,目的是消灭全人类…{f801}{f802}知道了这些的健二…{f801}为了阻止『神迹』而倒向了恶魔一边。{f801}{f802}…从那之后{f801}已经过了25年。{f801}{ffff}</source>
    <target>{f812}女恶魔人{0000}{f87a}{9400}{f813}{0100}{0000}馥{0600}健二在你们这么大的时候{f801}原来也是恶魔讨伐队的成员。{f801}{f802}他最初是为了保护东京,才加入{f801}恶魔讨伐队和恶魔战斗的…{f801}{f802}但是,恶魔出现在东京,{f801}其实是神的意思,目的是消灭全人类…{f801}{f802}知道了这些的健二…{f801}为了阻止『神迹』而倒向了恶魔一边。{f801}{f802}…从那之后{f801}已经过了25年。{f801}{ffff}</target>
  </entry>
  <entry id="5">
    <source>{f812}女恶魔人{0000}{f87a}{9400}{f813}{0100}{0000}{eb65}{0600}仔细想想,是健二把东京所有人{f801}都变成了恶魔人和人畜…{f801}{f802}可能是因为惧怕外来者吧。{f801}虽然不知道是什么原理…{f801}{f802}但只有具有主体性的人类{f801}才能启动恶魔召唤程序。{f801}{f802}正是打倒了众多恶魔的健二{f801}才明白人类主体性的可怕吧…{f801}{ffff}</source>
    <target>{f812}女恶魔人{0000}{f87a}{9400}{f813}{0100}{0000}{eb65}{0600}仔细想想,是健二把东京所有人{f801}都变成了恶魔人和人畜…{f801}{f802}可能是因为惧怕外来者吧。{f801}虽然不知道是什么原理…{f801}{f802}但只有具有主体性的人类{f801}才能启动恶魔召唤程序。{f801}{f802}正是打倒了众多恶魔的健二{f801}才明白人类主体性的可怕吧…{f801}{ffff}</target>
  </entry>
  <entry id="6">
    <source>{f812}女恶魔人{0000}{f87a}{9400}{f813}{0100}{0000}{eb65}{0600}仔细想想,是健二把东京所有人{f801}都变成了恶魔人和人畜…{f801}{f802}可能是因为惧怕外来者吧。{f801}虽然不知道是什么原理…{f801}{f802}但只有具有主体性的人类{f801}才能启动恶魔召唤程序。{f801}{f802}正是打倒了众多恶魔的健二{f801}才明白人类主体性的可怕吧…{f801}{ffff}</source>
    <target>{f812}女恶魔人{0000}{f87a}{9400}{f813}{0100}{0000}{eb65}{0600}仔细想想,是健二把东京所有人{f801}都变成了恶魔人和人畜…{f801}{f802}可能是因为惧怕外来者吧。{f801}虽然不知道是什么原理…{f801}{f802}但只有具有主体性的人类{f801}才能启动恶魔召唤程序。{f801}{f802}正是打倒了众多恶魔的健二{f801}才明白人类主体性的可怕吧…{f801}{ffff}</target>
  </entry>
  <entry id="7">
    <source>{f812}女性人畜{0000}{f87a}{6e00}{f813}{0100}{0000}{2f28}{0600}人畜这一选择也意外地有人气哦。{f801}没有战斗的必要,{f801}{f802}而且恶魔人也不会杀我们,{f801}不然的话…他们就会饿死。{f801}{ffff}</source>
    <target>{f812}女性人畜{0000}{f87a}{6e00}{f813}{0100}{0000}{2f28}{0600}人畜这一选择也意外地有人气哦。{f801}没有战斗的必要,{f801}{f802}而且恶魔人也不会杀我们,{f801}不然的话…他们就会饿死。{f801}{ffff}</target>
  </entry>
  <entry id="8">
    <source>{f812}女性人畜{0000}{f87a}{6e00}{f813}{0100}{0000}{2f28}{0600}呆在霞关这里,感觉之前在市谷的日子{f801}就像不曾存在过一样…{f801}{f802}之前有过很多很多的家伙来挑战健二,{f801}虽说最近是急剧减少了。{f801}{f802}那时,市谷每天都是一片火海,{f801}受波及而丧命的…好多都是我的熟人。{f801}{f802}各街区的人畜…{f801}都是从市谷逃命出来的。{f801}{ffff}</source>
    <target>{f812}女性人畜{0000}{f87a}{6e00}{f813}{0100}{0000}{2f28}{0600}呆在霞关这里,感觉之前在市谷的日子{f801}就像不曾存在过一样…{f801}{f802}之前有过很多很多的家伙来挑战健二,{f801}虽说最近是急剧减少了。{f801}{f802}那时,市谷每天都是一片火海,{f801}受波及而丧命的…好多都是我的熟人。{f801}{f802}各街区的人畜…{f801}都是从市谷逃命出来的。{f801}{ffff}</target>
  </entry>
  <entry id="9">
    <source>{f812}男恶魔人{0000}{f87a}{6700}{f813}{0100}{0000}{8555}{0600}哪个蠢货在大声说话?{f801}我听到是指挥室传来的声音。{f801}{f802}要是太吵的话{f801}阿辉会生气的。{f801}{ffff}</source>
    <target>{f812}男恶魔人{0000}{f87a}{6700}{f813}{0100}{0000}{8555}{0600}哪个蠢货在大声说话?{f801}我听到是指挥室传来的声音。{f801}{f802}要是太吵的话{f801}阿辉会生气的。{f801}{ffff}</target>
  </entry>
  <entry id="10">
    <source>{f812}男恶魔人{0000}{f87a}{6700}{f813}{0100}{0000}ゞ{0600}对了,你们是从哪来的?{f801}电梯那边是有守卫的吧?{f801}{f802}突然从指挥室出现…{f801}这是什么幻觉?{f801}{ffff}</source>
    <target>{f812}男恶魔人{0000}{f87a}{6700}{f813}{0100}{0000}ゞ{0600}对了,你们是从哪来的?{f801}电梯那边是有守卫的吧?{f801}{f802}突然从指挥室出现…{f801}这是什么幻觉?{f801}{ffff}</target>
  </entry>
  <entry id="11">
    <source>{f812}约纳坦{0000}{f87a}{0300}{f813}{0100}{0000}{e61a}{0600}外来者…就是指我们吧。{f801}{f802}看来我们的情况{f801}比想象中还要危险。{f801}{f802}和辉阁下一同行动{f801}也许是个明智的选择。{f801}{ffff}</source>
    <target>{f812}约纳坦{0000}{f87a}{0300}{f813}{0100}{0000}{e61a}{0600}外来者…就是指我们吧。{f801}{f802}看来我们的情况{f801}比想象中还要危险。{f801}{f802}和辉阁下一同行动{f801}也许是个明智的选择。{f801}{ffff}</target>
  </entry>
  <entry id="12">
    <source>{f812}男恶魔人{0000}{f87a}{6700}{f813}{0100}{0000}{7e55}{0600}健二从前也有过同伴。那是他在{f801}恶魔讨伐队时代的战友…一个男的。{f801}{f802}我在还是人类的时候{f801}还被那个人救过一次。{f801}{f802}…那人的身形和给人的感觉{f801}都很像那边那个扎马尾的小哥。{f801}{f802}但是那家伙…听说在战斗中{f801}为了保护健二被恶魔给杀了。{f801}{ffff}</source>
    <target>{f812}男恶魔人{0000}{f87a}{6700}{f813}{0100}{0000}{7e55}{0600}健二从前也有过同伴。那是他在{f801}恶魔讨伐队时代的战友…一个男的。{f801}{f802}我在还是人类的时候{f801}还被那个人救过一次。{f801}{f802}…那人的身形和给人的感觉{f801}都很像那边那个扎马尾的小哥。{f801}{f802}但是那家伙…听说在战斗中{f801}为了保护健二被恶魔给杀了。{f801}{ffff}</target>
  </entry>
  <entry id="13">
    <source>{f812}男恶魔人{0000}{f87a}{6700}{f813}{0100}{0000}{7e55}{0600}健二从前也有过同伴。那是他在{f801}恶魔讨伐队时代的战友…一个男的。{f801}{f802}但是听说那家伙…在战斗中{f801}为了保护健二被恶魔给杀了。{f801}{f802}不管拥有多强大的仲魔,{f801}『人类的血肉之躯总是脆弱的』…{f801}{f802}…好像就是以此为契机,{f801}健二那家伙决定了成为恶魔人。{f801}{ffff}</source>
    <target>{f812}男恶魔人{0000}{f87a}{6700}{f813}{0100}{0000}{7e55}{0600}健二从前也有过同伴。那是他在{f801}恶魔讨伐队时代的战友…一个男的。{f801}{f802}但是听说那家伙…在战斗中{f801}为了保护健二被恶魔给杀了。{f801}{f802}不管拥有多强大的仲魔,{f801}『人类的血肉之躯总是脆弱的』…{f801}{f802}…好像就是以此为契机,{f801}健二那家伙决定了成为恶魔人。{f801}{ffff}</target>
  </entry>
  <entry id="14">
    <source>{f812}男恶魔人{0000}{f87a}{6700}{f813}{0100}{0000}{7e55}{0600}前东京王从前也有过同伴。那是他在{f801}恶魔讨伐队时代的战友…一个男的。{f801}{f802}但是听说那家伙…在战斗中{f801}为了保护健二被恶魔给杀了。{f801}{f802}不管拥有多强大的仲魔,{f801}『人类的血肉之躯总是脆弱的』…{f801}{f802}…好像就是以此为契机,{f801}健二那家伙决定了成为恶魔人。{f801}{ffff}</source>
    <target>{f812}男恶魔人{0000}{f87a}{6700}{f813}{0100}{0000}{7e55}{0600}前东京王从前也有过同伴。那是他在{f801}恶魔讨伐队时代的战友…一个男的。{f801}{f802}但是听说那家伙…在战斗中{f801}为了保护健二被恶魔给杀了。{f801}{f802}不管拥有多强大的仲魔,{f801}『人类的血肉之躯总是脆弱的』…{f801}{f802}…好像就是以此为契机,{f801}健二那家伙决定了成为恶魔人。{f801}{ffff}</target>
  </entry>
  <entry id="101">
    <source>{f812}男性人畜{0000}{f87a}{6b00}{f813}{0100}{0000}{cb27}{0600}我跟辉说过了,{f801}我要留在霞关。{f801}{f802}因为恶魔人的缘故,我动起来很累,{f801}而且腿的肌肉也退化了…走不动了。{f801}{f802}嘛,我在还是人类的时候,{f801}就觉得新宿乱七八糟的很讨厌了…{f801}{ffff}</source>
    <target>{f812}男性人畜{0000}{f87a}{6b00}{f813}{0100}{0000}{cb27}{0600}我跟辉说过了,{f801}我要留在霞关。{f801}{f802}因为恶魔人的缘故,我动起来很累,{f801}而且腿的肌肉也退化了…走不动了。{f801}{f802}嘛,我在还是人类的时候,{f801}就觉得新宿乱七八糟的很讨厌了…{f801}{ffff}</target>
  </entry>
  <entry id="201">
    <source>{f812}男性人畜{0000}{f87a}{6b00}{f813}{0100}{0000}{cb27}{0600}阿辉王说要把东京变成{f801}『人人平等生活的东京』。{f801}{f802}…明明是个恶魔人{f801}说的话还真挺豪气,呵呵…{f801}{f802}那我就立志成为究极畜生人,{f801}成为连美食家都赞不绝口的人畜。{f801}{ffff}</source>
    <target>{f812}男性人畜{0000}{f87a}{6b00}{f813}{0100}{0000}{cb27}{0600}阿辉王说要把东京变成{f801}『人人平等生活的东京』。{f801}{f802}…明明是个恶魔人{f801}说的话还真挺豪气,呵呵…{f801}{f802}那我就立志成为究极畜生人,{f801}成为连美食家都赞不绝口的人畜。{f801}{ffff}</target>
  </entry>
  <entry id="301">
    <source>{f812}男性人畜{0000}{f87a}{6b00}{f813}{0100}{0000}{cb27}{0600}阿辉王说要把东京变成{f801}『人人平等生活的东京』。{f801}{f802}那恶魔人吃人畜{f801}这一点他打算怎么办?{f801}{f802}…他的话全是槽点,{f801}但既然他这样说了,我就好好期待吧。{f801}{ffff}</source>
    <target>{f812}男性人畜{0000}{f87a}{6b00}{f813}{0100}{0000}{cb27}{0600}阿辉王说要把东京变成{f801}『人人平等生活的东京』。{f801}{f802}那恶魔人吃人畜{f801}这一点他打算怎么办?{f801}{f802}…他的话全是槽点,{f801}但既然他这样说了,我就好好期待吧。{f801}{ffff}</target>
  </entry>
</mbm>