<mbm>
  <entry id="0">
    <source>ホープである{f801}{f816}辺境{f817}へんきょう{f818}の{f816}村{f817}むら{f818}で{f816}全身{f817}ぜんしん{f818}が{f816}黒{f817}くろ{f818}ずみ{f816}死{f817}し{f818}に{f816}到{f817}いた{f818}る{f816}奇病{f817}きびょう{f818}が{f816}発生{f817}はっせい{f818}している{f801}これは{f816}病気{f817}びょうき{f818}ではなく{f816}悪魔{f817}あくま{f818}の{f816}呪{f817}のろ{f818}い…ナラクの{f804}{0500}{f816}第{f817}だい{f818}3{f816}層{f817}そう{f818}{f804}{0000}で{f801}{f816}呪{f817}のろ{f818}いの{f816}舞踏{f817}ぶとう{f818}を{f816}行{f817}おこな{f818}う{f816}悪霊{f817}あくりょう{f818}$マカーブルが{f816}原因{f817}げんいん{f818}と{f816}判明{f817}はんめい{f818}した{f801}{f804}{0500}{f816}不吉{f817}ふきつ{f818}の{f816}群{f817}む{f818}れ{f804}{0000}を{f816}全滅{f817}ぜんめつ{f818}せよ だがマカーブルに{f816}似{f817}に{f818}た{f801}{f816}悪魔{f817}あくま{f818}の{f816}報告{f817}ほうこく{f818}もあるので{f816}気{f817}き{f818}をつけろ {f816}以上{f817}いじょう{f818}である{f801}{ffff}</source>
    <target>ホープである{f801}{f816}辺境{f817}へんきょう{f818}の{f816}村{f817}むら{f818}で{f816}全身{f817}ぜんしん{f818}が{f816}黒{f817}くろ{f818}ずみ{f816}死{f817}し{f818}に{f816}到{f817}いた{f818}る{f816}奇病{f817}きびょう{f818}が{f816}発生{f817}はっせい{f818}している{f801}これは{f816}病気{f817}びょうき{f818}ではなく{f816}悪魔{f817}あくま{f818}の{f816}呪{f817}のろ{f818}い…ナラクの{f804}{0500}{f816}第{f817}だい{f818}3{f816}層{f817}そう{f818}{f804}{0000}で{f801}{f816}呪{f817}のろ{f818}いの{f816}舞踏{f817}ぶとう{f818}を{f816}行{f817}おこな{f818}う{f816}悪霊{f817}あくりょう{f818}$マカーブルが{f816}原因{f817}げんいん{f818}と{f816}判明{f817}はんめい{f818}した{f801}{f804}{0500}{f816}不吉{f817}ふきつ{f818}の{f816}群{f817}む{f818}れ{f804}{0000}を{f816}全滅{f817}ぜんめつ{f818}せよ だがマカーブルに{f816}似{f817}に{f818}た{f801}{f816}悪魔{f817}あくま{f818}の{f816}報告{f817}ほうこく{f818}もあるので{f816}気{f817}き{f818}をつけろ {f816}以上{f817}いじょう{f818}である{f801}{ffff}</target>
  </entry>
  <entry id="1">
    <source>納品クエストの説明文テンプレ 2回目{f801}クリア条件:{f801}{f872}{0100}を{f878}{0100}個持ってくる{f801}{f872}{0200}を{f878}{0200}個持ってくる{f801}{f872}{0300}を{f878}{0300}個持ってくる{f801}報酬:{f801}{f872}{0400} {f878}{0400}個{f801}{ffff}</source>
    <target>納品クエストの説明文テンプレ 2回目{f801}クリア条件:{f801}{f872}{0100}を{f878}{0100}個持ってくる{f801}{f872}{0200}を{f878}{0200}個持ってくる{f801}{f872}{0300}を{f878}{0300}個持ってくる{f801}報酬:{f801}{f872}{0400} {f878}{0400}個{f801}{ffff}</target>
  </entry>
</mbm>