<mbm>
  <entry id="0">
    <source>{f812}男人的声音{0000}{f87a}{0200}{f813}{0000}{0000}{4959}{0400}停停!给我停下!{f801}{ffff}</source>
    <target>{f812}男人的声音{0000}{f87a}{0200}{f813}{0000}{0000}{4959}{0400}停停!给我停下!{f801}{ffff}</target>
  </entry>
  <entry id="1">
    <source>一个男人突然跑过来拦在了面前{f801}{ffff}</source>
    <target>一个男人突然跑过来拦在了面前{f801}{ffff}</target>
  </entry>
  <entry id="2">
    <source>{f812}直觉敏锐的男人{0000}{f87a}{7600}{f813}{0000}{0000}{4a59}{0400}呼…不好意思啦小子,{f801}此路不通。{f801}{f802}{f813}{0000}{0000}{4b59}{0400}老子就是人称终端看守的{f801}拥有二十年守卫经验的老兵。{f801}{ffff}</source>
    <target>{f812}直觉敏锐的男人{0000}{f87a}{7600}{f813}{0000}{0000}{4a59}{0400}呼…不好意思啦小子,{f801}此路不通。{f801}{f802}{f813}{0000}{0000}{4b59}{0400}老子就是人称终端看守的{f801}拥有二十年守卫经验的老兵。{f801}{ffff}</target>
  </entry>
  <entry id="3">
    <source>{f812}直觉敏锐的男人{0000}{f87a}{7600}{f813}{0000}{0000}{4c59}{0400}…哦?你不是之前那小子吗!{f801}那时候你竟敢…{f801}{f802}{f813}{0000}{0000}{4d59}{0400}…算了!那种事先放一边,{f801}我看守人的直觉可是直中要害哦。{f801}{ffff}</source>
    <target>{f812}直觉敏锐的男人{0000}{f87a}{7600}{f813}{0000}{0000}{4c59}{0400}…哦?你不是之前那小子吗!{f801}那时候你竟敢…{f801}{f802}{f813}{0000}{0000}{4d59}{0400}…算了!那种事先放一边,{f801}我看守人的直觉可是直中要害哦。{f801}{ffff}</target>
  </entry>
  <entry id="4">
    <source>{f812}直觉敏锐的男人{0000}{f87a}{7600}{f813}{0000}{0000}{4e59}{0400}果然是你啊…真是好险。{f801}自我介绍就可以免了。{f801}{f802}{f813}{0000}{0000}{4f59}{0400}既然我出现在这里…{f801}就代表这里有传送终端!{f801}{ffff}</source>
    <target>{f812}直觉敏锐的男人{0000}{f87a}{7600}{f813}{0000}{0000}{4e59}{0400}果然是你啊…真是好险。{f801}自我介绍就可以免了。{f801}{f802}{f813}{0000}{0000}{4f59}{0400}既然我出现在这里…{f801}就代表这里有传送终端!{f801}{ffff}</target>
  </entry>
  <entry id="5">
    <source>{f812}直觉敏锐的男人{0000}{f87a}{7600}{f813}{0000}{0000}{5059}{0400}你就是我的宿敌…{f801}全东京的终端都多亏你关照了啊!{f801}{f802}{f813}{0000}{0000}{5159}{0400}为了养活家里人,{f801}我一直孤身在外打拼…{f801}{f802}{f813}{0000}{0000}{5259}{0400}多年累积起来的直觉告诉我,{f801}这里有那个东西!{f801}{ffff}</source>
    <target>{f812}直觉敏锐的男人{0000}{f87a}{7600}{f813}{0000}{0000}{5059}{0400}你就是我的宿敌…{f801}全东京的终端都多亏你关照了啊!{f801}{f802}{f813}{0000}{0000}{5159}{0400}为了养活家里人,{f801}我一直孤身在外打拼…{f801}{f802}{f813}{0000}{0000}{5259}{0400}多年累积起来的直觉告诉我,{f801}这里有那个东西!{f801}{ffff}</target>
  </entry>
  <entry id="6">
    <source>{f812}直觉敏锐的男人{0000}{f87a}{7600}{f813}{0000}{0000}{5459}{0400}只要有传送终端在我身后,{f801}我就要杀掉一切来犯者!{f801}{ffff}</source>
    <target>{f812}直觉敏锐的男人{0000}{f87a}{7600}{f813}{0000}{0000}{5459}{0400}只要有传送终端在我身后,{f801}我就要杀掉一切来犯者!{f801}{ffff}</target>
  </entry>
  <entry id="7">
    <source>结界消解了…{f801}{ffff}</source>
    <target>结界消解了…{f801}{ffff}</target>
  </entry>
  <entry id="8">
    <source>{f812}巴洛斯{0000}{f87a}{0200}{f813}{0100}{0000}{bf1a}{0600}任务的进展非常顺利呢。{f801}{ffff}</source>
    <target>{f812}巴洛斯{0000}{f87a}{0200}{f813}{0100}{0000}{bf1a}{0600}任务的进展非常顺利呢。{f801}{ffff}</target>
  </entry>
  <entry id="9">
    <source>{f812}巴洛斯{0000}{f87a}{0200}{f813}{0100}{0000}{be1a}{0600}扫描模式启动…{f801}{ffff}</source>
    <target>{f812}巴洛斯{0000}{f87a}{0200}{f813}{0100}{0000}{be1a}{0600}扫描模式启动…{f801}{ffff}</target>
  </entry>
  <entry id="10">
    <source>{f812}巴洛斯{0000}{f87a}{0200}{f813}{0000}{0000}{1521}{0100}这个空间似乎也是传送终端的一种,{f801}启动程序已正常运行。{f801}{f802}{f813}{0100}{0000}{d630}{0600}这里是{f801}炼狱传送终端。{f801}{f802}{f813}{0000}{0000}{1321}{0100}与其他传送终端连接OK,{f801}可以使用传送功能了。{f801}{ffff}</source>
    <target>{f812}巴洛斯{0000}{f87a}{0200}{f813}{0000}{0000}{1521}{0100}这个空间似乎也是传送终端的一种,{f801}启动程序已正常运行。{f801}{f802}{f813}{0100}{0000}{d630}{0600}这里是{f801}炼狱传送终端。{f801}{f802}{f813}{0000}{0000}{1321}{0100}与其他传送终端连接OK,{f801}可以使用传送功能了。{f801}{ffff}</target>
  </entry>
</mbm>