<mbm>
  <entry id="0">
    <source>{f812}伊萨卡{0000}{f87a}{0000}{f813}{0000}{0000}{3996}{0400}呃呃呃…呜啊啊啊啊…{f801}咿啊啊啊啊啊啊…{f801}{ffff}</source>
    <target>{f812}伊萨卡{0000}{f87a}{0000}{f813}{0000}{0000}{3996}{0400}呃呃呃…呜啊啊啊啊…{f801}咿啊啊啊啊啊啊…{f801}{ffff}</target>
  </entry>
  <entry id="1">
    <source>{f812}伊萨卡{0000}{f87a}{0000}{f813}{0000}{0000}{3a96}{0400}{f843}{0000}…我没能成为一名武士,{f801}真的很痛苦。{f801}{f802}{f813}{0000}{0000}{3b96}{0400}但是,读过黑武士给我的书之后,{f801}我又振作了起来…{f801}{f802}{f813}{0000}{0000}{3c96}{0400}真的很高兴…我有生以来第一次,{f801}觉得沉浸在什么东西当中…{f801}{f802}{f813}{0000}{0000}{3d96}{0400}然后,愤怒涌上我的心头。{f801}{f802}{f813}{0000}{0000}{3e96}{0400}我意识到,我之所以会变成这样{f801}全都是富裕层的错!{f801}{ffff}</source>
    <target>{f812}伊萨卡{0000}{f87a}{0000}{f813}{0000}{0000}{3a96}{0400}{f843}{0000}…我没能成为一名武士,{f801}真的很痛苦。{f801}{f802}{f813}{0000}{0000}{3b96}{0400}但是,读过黑武士给我的书之后,{f801}我又振作了起来…{f801}{f802}{f813}{0000}{0000}{3c96}{0400}真的很高兴…我有生以来第一次,{f801}觉得沉浸在什么东西当中…{f801}{f802}{f813}{0000}{0000}{3d96}{0400}然后,愤怒涌上我的心头。{f801}{f802}{f813}{0000}{0000}{3e96}{0400}我意识到,我之所以会变成这样{f801}全都是富裕层的错!{f801}{ffff}</target>
  </entry>
  <entry id="2">
    <source>{f812}伊萨卡{0000}{f87a}{0000}{f813}{0000}{0000}{4896}{0400}怎么了,富裕层的大人只有这点{f801}能耐吗?这就是你的全力了吗?{f801}{f802}{f813}{0000}{0000}{4996}{0400}你不是根本瞧不起我吗?{f801}来把我踩在脚下啊!{f801}{ffff}</source>
    <target>{f812}伊萨卡{0000}{f87a}{0000}{f813}{0000}{0000}{4896}{0400}怎么了,富裕层的大人只有这点{f801}能耐吗?这就是你的全力了吗?{f801}{f802}{f813}{0000}{0000}{4996}{0400}你不是根本瞧不起我吗?{f801}来把我踩在脚下啊!{f801}{ffff}</target>
  </entry>
  <entry id="3">
    <source>{f812}伊萨卡{0000}{f87a}{0000}{f813}{0000}{0000}{4a96}{0400}{f843}{0000}…别移开你的视线…{f801}看着我这悲惨的模样…!{f801}{ffff}</source>
    <target>{f812}伊萨卡{0000}{f87a}{0000}{f813}{0000}{0000}{4a96}{0400}{f843}{0000}…别移开你的视线…{f801}看着我这悲惨的模样…!{f801}{ffff}</target>
  </entry>
  <entry id="4">
    <source>{f812}伊萨卡{0000}{f87a}{0000}{f813}{0000}{0000}{4b96}{0400}呃…好痛…{f801}血…止不住了…{f801}{f802}{f813}{0000}{0000}{4c96}{0400}拜托了,{f843}{0000}…{f801}给我个痛快…{f801}{f802}{f813}{0000}{0000}{4d96}{0400}用武士的手…{f801}用你的手给我一个了断吧…?{f801}{ffff}</source>
    <target>{f812}伊萨卡{0000}{f87a}{0000}{f813}{0000}{0000}{4b96}{0400}呃…好痛…{f801}血…止不住了…{f801}{f802}{f813}{0000}{0000}{4c96}{0400}拜托了,{f843}{0000}…{f801}给我个痛快…{f801}{f802}{f813}{0000}{0000}{4d96}{0400}用武士的手…{f801}用你的手给我一个了断吧…?{f801}{ffff}</target>
  </entry>
  <entry id="5">
    <source>刺向他的要害{f801}不刺向他的要害{f801}{ffff}</source>
    <target>刺向他的要害{f801}不刺向他的要害{f801}{ffff}</target>
  </entry>
  <entry id="6">
    <source>{f812}约纳坦{0000}{f87a}{0300}{f813}{0000}{0000}{4e96}{0400}你认真的吗,{f843}{0000}?{f801}做到这一步已经足够了吧!{f801}{ffff}</source>
    <target>{f812}约纳坦{0000}{f87a}{0300}{f813}{0000}{0000}{4e96}{0400}你认真的吗,{f843}{0000}?{f801}做到这一步已经足够了吧!{f801}{ffff}</target>
  </entry>
  <entry id="7">
    <source>{f812}沃尔特{0000}{f87a}{0400}{f813}{0000}{0000}{4f96}{0400}约纳坦…{f801}{ffff}</source>
    <target>{f812}沃尔特{0000}{f87a}{0400}{f813}{0000}{0000}{4f96}{0400}约纳坦…{f801}你的那种做法，并不是同情。{f801}{ffff}</target>
  </entry>
  <entry id="8">
    <source>{f812}约纳坦{0000}{f87a}{0300}{f813}{0000}{0000}{5096}{0400}…你说什么?{f801}{ffff}</source>
    <target>{f812}约纳坦{0000}{f87a}{0300}{f813}{0000}{0000}{5096}{0400}…你说什么?{f801}{ffff}</target>
  </entry>
  <entry id="9">
    <source>{f812}沃尔特{0000}{f87a}{0400}{f813}{0000}{0000}{5196}{0400}你那是『逃避』,{f801}转过身不去看痛苦的现实。{f801}{f802}{f813}{0000}{0000}{5296}{0400}向{f843}{0000}学习吧,{f801}抱定那种决心。{f801}{ffff}</source>
    <target>{f812}沃尔特{0000}{f87a}{0400}{f813}{0000}{0000}{5196}{0400}你那是『逃避』,{f801}转过身不去看痛苦的现实。{f801}{f802}{f813}{0000}{0000}{5296}{0400}向{f843}{0000}学习吧,{f801}抱定那种决心。{f801}{ffff}</target>
  </entry>
  <entry id="10">
    <source>{f812}约纳坦{0000}{f87a}{0300}{f813}{0000}{0000}{5396}{0400}呃…!{f801}{ffff}</source>
    <target>{f812}约纳坦{0000}{f87a}{0300}{f813}{0000}{0000}{5396}{0400}呃…!{f801}{ffff}</target>
  </entry>
  <entry id="11">
    <source>{f812}伊萨卡{0000}{f87a}{0000}{f813}{0000}{0000}{5496}{0400}谢谢你…{f801}{ffff}</source>
    <target>{f812}伊萨卡{0000}{f87a}{0000}{f813}{0000}{0000}{5496}{0400}谢谢你…{f801}{ffff}</target>
  </entry>
  <entry id="12">
    <source>{f812}沃尔特{0000}{f87a}{0400}{f813}{0000}{0000}{5596}{0400}你认真的吗,{f843}{0000}?{f801}{f802}{f813}{0000}{0000}{5696}{0400}那家伙已经不是人类了…{f801}他已经变成了恶魔啊?{f801}{f802}{f813}{0000}{0000}{5796}{0400}你在这里假装善良,{f801}只不过是在逃避现实。{f801}{f802}{f813}{0000}{0000}{5896}{0400}用你的手将他从痛苦中解救出来{f801}不就是最大的仁慈吗?{f801}{ffff}</source>
    <target>{f812}沃尔特{0000}{f87a}{0400}{f813}{0000}{0000}{5596}{0400}你认真的吗,{f843}{0000}?{f801}{f802}{f813}{0000}{0000}{5696}{0400}那家伙已经不是人类了…{f801}他已经变成了恶魔啊?{f801}{f802}{f813}{0000}{0000}{5796}{0400}你在这里假装善良,{f801}只不过是在逃避现实。{f801}{f802}{f813}{0000}{0000}{5896}{0400}用你的手将他从痛苦中解救出来{f801}不就是最大的仁慈吗?{f801}{ffff}</target>
  </entry>
  <entry id="13">
    <source>{f812}伊萨卡{0000}{f87a}{0000}{f813}{0000}{0000}{5996}{0400}嘎啊啊啊啊…!{f801}{f802}{f813}{0000}{0000}{5a96}{0400}{f843}{0000}…为什么要让我{f801}继续受苦啊啊啊啊啊…!{f801}{ffff}</source>
    <target>{f812}伊萨卡{0000}{f87a}{0000}{f813}{0000}{0000}{5996}{0400}嘎啊啊啊啊…!{f801}{f802}{f813}{0000}{0000}{5a96}{0400}{f843}{0000}…为什么要让我{f801}继续受苦啊啊啊啊啊…!{f801}{ffff}</target>
  </entry>
  <entry id="14">
    <source>{f812}伊萨卡{0000}{f87a}{0700}{f813}{0000}{0000}{5b96}{0400}啊…啊…这里好黑…{f801}我…我什么也看不到了…{f801}{f802}{f813}{0000}{0000}{5c96}{0400}…{f801}{f843}{0000}是…你吗…?{f801}{ffff}</source>
    <target>{f812}伊萨卡{0000}{f87a}{0700}{f813}{0000}{0000}{5b96}{0400}啊…啊…这里好黑…{f801}我…我什么也看不到了…{f801}{f802}{f813}{0000}{0000}{5c96}{0400}…{f801}{f843}{0000}是…你吗…?{f801}{ffff}</target>
  </entry>
  <entry id="15">
    <source>{f812}伊萨卡{0000}{f87a}{0700}{f813}{0000}{0000}{5d96}{0400}你还记得吗…?我们给村里跑腿…{f801}第一次…去御门城的那天…{f801}{f802}{f813}{0000}{0000}{5e96}{0400}我们发誓…{f801}绝对要…成为武士…{f801}{f802}{f813}{0000}{0000}{5f96}{0400}在御门湖…湖畔…{f801}充满回忆的…地方…{f801}{ffff}</source>
    <target>{f812}伊萨卡{0000}{f87a}{0700}{f813}{0000}{0000}{5d96}{0400}你还记得吗…?我们给村里跑腿…{f801}第一次…去御门城的那天…{f801}{f802}{f813}{0000}{0000}{5e96}{0400}我们发誓…{f801}绝对要…成为武士…{f801}{f802}{f813}{0000}{0000}{5f96}{0400}在御门湖…湖畔…{f801}充满回忆的…地方…{f801}{ffff}</target>
  </entry>
  <entry id="16">
    <source>{f812}伊萨卡{0000}{f87a}{0700}{f813}{0000}{0000}{6096}{0400}{f843}{0000}…你要{f801}成为一名…了不起的武士…{f801}{f802}{f813}{0000}{0000}{6196}{0400}改变这个…世界…{f801}{ffff}</source>
    <target>{f812}伊萨卡{0000}{f87a}{0700}{f813}{0000}{0000}{6096}{0400}{f843}{0000}…你要{f801}成为一名…了不起的武士…{f801}{f802}{f813}{0000}{0000}{6196}{0400}改变这个…世界…{f801}{ffff}</target>
  </entry>
  <entry id="1000">
    <source>{f812}伊萨卡{0000}{f87a}{0000}{f813}{0000}{0000}{3f96}{0400}{f843}{0000}…告诉我你的心里话。{f801}{f802}{f813}{0000}{0000}{4096}{0400}你成为武士之后,你的心{f801}是否也变得像是属于富裕层了?{f801}{f802}{f813}{0000}{0000}{4196}{0400}还是说…仍然属于贫民层?{f801}{ffff}</source>
    <target>{f812}伊萨卡{0000}{f87a}{0000}{f813}{0000}{0000}{3f96}{0400}{f843}{0000}…告诉我你的心里话。{f801}{f802}{f813}{0000}{0000}{4096}{0400}你成为武士之后,你的心{f801}是否也变得像是属于富裕层了?{f801}{f802}{f813}{0000}{0000}{4196}{0400}还是说…仍然属于贫民层?{f801}{ffff}</target>
  </entry>
  <entry id="1001">
    <source>我属于富裕层{f801}我属于贫民层{f801}无视他并继续战斗{f801}{ffff}</source>
    <target>我属于富裕层{f801}我属于贫民层{f801}无视他并继续战斗{f801}{ffff}</target>
  </entry>
  <entry id="1002">
    <source>{f812}伊萨卡{0000}{f87a}{0000}{f813}{0000}{0000}{4296}{0400}这样啊…{f801}作为你的好友,我祝愿你出人头地…{f801}{f802}{f813}{0000}{0000}{4396}{0400}…你觉得有可能吗!{f801}怕不是昏了头吧!{f801}{f802}{f813}{0000}{0000}{4496}{0400}你这种连心都出卖给富裕层的家伙,{f801}别说是我的朋友,简直连屁都不是!{f801}{ffff}</source>
    <target>{f812}伊萨卡{0000}{f87a}{0000}{f813}{0000}{0000}{4296}{0400}这样啊…{f801}作为你的好友,我祝愿你出人头地…{f801}{f802}{f813}{0000}{0000}{4396}{0400}…你觉得有可能吗!{f801}怕不是昏了头吧!{f801}{f802}{f813}{0000}{0000}{4496}{0400}你这种连心都出卖给富裕层的家伙,{f801}别说是我的朋友,简直连屁都不是!{f801}{ffff}</target>
  </entry>
  <entry id="1003">
    <source>{f801}与同伴{f843}{0000}在伊萨卡勇猛的气魄前退缩了!{f801}{ffff}</source>
    <target>{f801}与同伴{f843}{0000}在伊萨卡勇猛的气魄前退缩了!{f801}{ffff}</target>
  </entry>
  <entry id="1004">
    <source>伊萨卡{f801}获得了行动机会!{f801}{ffff}</source>
    <target>伊萨卡{f801}获得了行动机会!{f801}{ffff}</target>
  </entry>
  <entry id="1005">
    <source>{f812}伊萨卡{0000}{f87a}{0000}{f813}{0000}{0000}{4596}{0400}这…这不可能?!{f801}你少在这里说好听话!{f801}{f802}{f813}{0000}{0000}{4696}{0400}怎么会这样…那我…{f801}我都做了些什么…{f801}{f802}{f813}{0000}{0000}{4796}{0400}呃啊啊啊…!{f801}{ffff}</source>
    <target>{f812}伊萨卡{0000}{f87a}{0000}{f813}{0000}{0000}{4596}{0400}这…这不可能?!{f801}你少在这里说好听话!{f801}{f802}{f813}{0000}{0000}{4696}{0400}怎么会这样…那我…{f801}我都做了些什么…{f801}{f802}{f813}{0000}{0000}{4796}{0400}呃啊啊啊…!{f801}{ffff}</target>
  </entry>
  <entry id="1006">
    <source>伊萨卡在痛苦中挣扎!{f801}{ffff}</source>
    <target>伊萨卡在痛苦中挣扎!{f801}{ffff}</target>
  </entry>
  <entry id="1007">
    <source>伊萨卡错过了行动的时机!{f801}{ffff}</source>
    <target>伊萨卡错过了行动的时机!{f801}{ffff}</target>
  </entry>
  <entry id="1008">
    <source>{f843}{0000}{f801}无视了伊萨卡并继续战斗…{f801}{ffff}</source>
    <target>{f843}{0000}{f801}无视了伊萨卡并继续战斗…{f801}{ffff}</target>
  </entry>
</mbm>