<mbm>
  <entry id="0">
    <source>房间深处站着一个恶魔…{f801}{f802}恶魔警惕地看着{f801}{f843}{0000}…{f801}{f802}{f843}{0000}解释了{f801}事情的来龙去脉。{f801}{ffff}</source>
    <target>房间深处站着一个恶魔…{f801}{f802}恶魔警惕地看着{f801}{f843}{0000}…{f801}{f802}{f843}{0000}解释了{f801}事情的来龙去脉。{f801}{ffff}</target>
  </entry>
  <entry id="1">
    <source>{f812}莫克伊{0000}{f87a}{26fe}{f813}{0100}{0000}{bd90}{0700}杰克灯笼在找我…{f801}是这样吗?{f801}{f802}原来如此…看来是{f801}让他担心了啊。{f801}{f802}的确,我一直在帮助{f801}那些被人类和恶魔{f801}袭击的弱小恶魔,{f801}{f802}把他们安置到一个{f801}相对安全的地方,{f801}叫做奈落。{f801}{f802}但说到底魔傀就是魔傀{f801}起初还能应付,{f801}{f802}但对付强大的恶魔{f801}力不从心,在涩谷{f801}自身难保。{f801}{f802}可我不能就这么回去。{f801}{f802}不知不觉间,我已经{f801}成了他们的英雄。{f801}{f802}如果现在回去,{f801}就不再是英雄了。{ffff}</source>
    <target>{f812}莫克伊{0000}{f87a}{26fe}{f813}{0100}{0000}{bd90}{0700}杰克灯笼在找我…{f801}是这样吗?{f801}{f802}原来如此…看来是{f801}让他担心了啊。{f801}{f802}的确,我一直在帮助{f801}那些被人类和恶魔{f801}袭击的弱小恶魔,{f801}{f802}把他们安置到一个{f801}相对安全的地方,{f801}叫做奈落。{f801}{f802}但说到底魔傀就是魔傀{f801}起初还能应付,{f801}{f802}但对付强大的恶魔{f801}力不从心,在涩谷{f801}自身难保。{f801}{f802}可我不能就这么回去。{f801}{f802}不知不觉间,我已经{f801}成了他们的英雄。{f801}{f802}如果现在回去,{f801}就不再是英雄了。{ffff}</target>
  </entry>
  <entry id="2">
    <source>莫克伊终究是莫克伊{f801}朋友会伤心的{f801}向英雄大人致敬{f801}{ffff}</source>
    <target>莫克伊终究是莫克伊{f801}朋友会伤心的{f801}向英雄大人致敬{f801}{ffff}</target>
  </entry>
  <entry id="3">
    <source>{f812}莫克伊{0000}{f87a}{26fe}{f813}{0100}{0000}{bd90}{0700}虽说是我自己说的,{f801}但被人类这么说{f801}还真不是滋味。{f801}{f802}我可是在老家{f801}也算个大恶灵啊。{f801}{f802}………{f801}{f802}{f813}{0100}{0000}{b890}{0700}不过,还是要谢谢你{f801}说了这番话。{f801}{f802}看来是时候{f801}该收手了。{f801}{ffff}</source>
    <target>{f812}莫克伊{0000}{f87a}{26fe}{f813}{0100}{0000}{bd90}{0700}虽说是我自己说的,{f801}但被人类这么说{f801}还真不是滋味。{f801}{f802}我可是在老家{f801}也算个大恶灵啊。{f801}{f802}………{f801}{f802}{f813}{0100}{0000}{b890}{0700}不过,还是要谢谢你{f801}说了这番话。{f801}{f802}看来是时候{f801}该收手了。{f801}{ffff}</target>
  </entry>
  <entry id="4">
    <source>{f812}莫克伊{0000}{f87a}{26fe}{f813}{0100}{0000}{bd90}{0700}伤心?我不再是英雄了,{f801}难道还有这个价值?{f801}{f802}………{f801}{f802}{f813}{0100}{0000}{b890}{0700}这样啊…你是说{f801}活着回去更重要吗…{f801}{ffff}</source>
    <target>{f812}莫克伊{0000}{f87a}{26fe}{f813}{0100}{0000}{bd90}{0700}伤心?我不再是英雄了,{f801}难道还有这个价值?{f801}{f802}………{f801}{f802}{f813}{0100}{0000}{b890}{0700}这样啊…你是说{f801}活着回去更重要吗…{f801}{ffff}</target>
  </entry>
  <entry id="5">
    <source>{f812}莫克伊{0000}{f87a}{26fe}{f813}{0100}{0000}{bd90}{0700}说是英雄,{f801}{f802}其实也没做什么了不起的事,{f801}也算不上什么大人物。{f801}{f802}………{f801}{f802}{f813}{0100}{0000}{b890}{0700}原来如此,{f801}我到底在执意些什么呢。{f801}{f802}谢谢你,人类{f801}让我明白了什么才是最重要的{f801}{ffff}</source>
    <target>{f812}莫克伊{0000}{f87a}{26fe}{f813}{0100}{0000}{bd90}{0700}说是英雄,{f801}{f802}其实也没做什么了不起的事,{f801}也算不上什么大人物。{f801}{f802}………{f801}{f802}{f813}{0100}{0000}{b890}{0700}原来如此,{f801}我到底在执意些什么呢。{f801}{f802}谢谢你,人类{f801}让我明白了什么才是最重要的{f801}{ffff}</target>
  </entry>
  <entry id="6">
    <source>{f812}莫克伊{0000}{f87a}{26fe}我明白了,在下夜魔莫克伊。{f801}虽然有不好意思,但我这就回去!{f801}{ffff}</source>
    <target>{f812}莫克伊{0000}{f87a}{26fe}我明白了,在下夜魔莫克伊。{f801}虽然有不好意思,但我这就回去!{f801}{ffff}</target>
  </entry>
  <entry id="7">
    <source>莫克伊离开了{f801}{ffff}</source>
    <target>莫克伊离开了{f801}{ffff}</target>
  </entry>
  <entry id="900">
    <source>谁也不在…{f801}{ffff}</source>
    <target>谁也不在…{f801}{ffff}</target>
  </entry>
</mbm>