<mbm>
  <entry id="0">
    <source>{f816}壁{f817}かべ{f818}の{f816}向{f817}む{f818}こうから{f816}声{f817}こえ{f818}が{f816}聞{f817}き{f818}こえてくる…{f801}</source>
    <target>{f816}壁{f817}かべ{f818}の{f816}向{f817}む{f818}こうから{f816}声{f817}こえ{f818}が{f816}聞{f817}き{f818}こえてくる…{f801}</target>
  </entry>
  <entry id="1">
    <source>{f812}女の声{0000}{f813}{0100}{0000}{9f26}{0600}{f816}誰{f817}だれ{f818}かいるの…?{f801}{f802}ヒマだから{f816}話{f817}はな{f818}し{f816}相手{f817}あいて{f818}になってよぉ{f801}アタシ{f816}一応{f817}いちおう{f818} そういうののプロだから…{f801}</source>
    <target>{f812}女の声{0000}{f813}{0100}{0000}{9f26}{0600}{f816}誰{f817}だれ{f818}かいるの…?{f801}{f802}ヒマだから{f816}話{f817}はな{f818}し{f816}相手{f817}あいて{f818}になってよぉ{f801}アタシ{f816}一応{f817}いちおう{f818} そういうののプロだから…{f801}</target>
  </entry>
  <entry id="2">
    <source>{f812}女の声{0000}…やれ 『{f816}一晩{f817}ひとばん{f818}{f816}付{f817}つ{f818}き{f816}合{f817}あ{f818}え』だとか{f801}{f816}阿修羅会{f817}あしゅらかい{f818}も{f816}最悪{f817}さいあく{f818}は{f816}最悪{f817}さいあく{f818}なんだけどさ…{f801}{f802}でも {f816}殺{f817}ころ{f818}さないだけマシじゃない?{f801}{f816}悪魔{f817}あくま{f818}はね…{f816}喰{f817}た{f818}べちゃうのよ…?{f801}</source>
    <target>{f812}女の声{0000}…やれ 『{f816}一晩{f817}ひとばん{f818}{f816}付{f817}つ{f818}き{f816}合{f817}あ{f818}え』だとか{f801}{f816}阿修羅会{f817}あしゅらかい{f818}も{f816}最悪{f817}さいあく{f818}は{f816}最悪{f817}さいあく{f818}なんだけどさ…{f801}{f802}でも {f816}殺{f817}ころ{f818}さないだけマシじゃない?{f801}{f816}悪魔{f817}あくま{f818}はね…{f816}喰{f817}た{f818}べちゃうのよ…?{f801}</target>
  </entry>
  <entry id="3">
    <source>{f812}女の声{0000}みんな {f816}変革{f817}へんかく{f818}とかそういう{f816}言葉{f817}ことば{f818}{f801}{f816}好{f817}す{f818}きなのはわかるけどさ…{f801}{f802}{f816}妙{f817}みょう{f818}な{f816}正義感{f817}せいぎかん{f818}を{f816}振{f817}ふ{f818}りかざして{f801}ホント{f816}余計{f817}よけい{f818}なことをしてくれたわよねッ{f801}</source>
    <target>{f812}女の声{0000}みんな {f816}変革{f817}へんかく{f818}とかそういう{f816}言葉{f817}ことば{f818}{f801}{f816}好{f817}す{f818}きなのはわかるけどさ…{f801}{f802}{f816}妙{f817}みょう{f818}な{f816}正義感{f817}せいぎかん{f818}を{f816}振{f817}ふ{f818}りかざして{f801}ホント{f816}余計{f817}よけい{f818}なことをしてくれたわよねッ{f801}</target>
  </entry>
</mbm>